{
    "updated": "2025-04-01 21:52:20.725469",
    "ads": [
        {
            "title": "Peugeot 206XA na chodzie z vat1 i FV",
            "price": "1 650 złdo negocjacji",
            "link": "https://www.olx.pl/oferta/peugeot-206xa-na-chodzie-z-vat1-i-fv-CID5-ID1557IF.html",
            "description": "Witam, \n\nJakie auto każdy widzi i nie mamy nic do ukrycie, autko zarejestrowane jako ciężarowe i jeżdżące lecz troszkę zaniedbane bo służyło jako awaryjne itp. \nJeździ , hamuje nic się złego nie dzieje złego, na chodzie można jechać.\nPrzegląd aktualny do końca Kwietnia 25\nOC ważne do Marca 2026/ opłacona 1 rata   \nVat1  dow. rej.\n\nFV 1.650 zł brutto  \n\nAuto stoi w Lublinie przy Hutniczej 3 {dawna baza PKS }\n\nZapraszam",
            "details": {
                "Numer": "VIN: VF328HZA44904601",
                "Model:": "206",
                "Rok": "produkcji: 2005",
                "Paliwo:": "Diesel",
                "Typ": "nadwozia: Coupe",
                "Przebieg:": "268 000 km",
                "Kolor:": "Biały",
                "Poj.": "silnika: 1 400 cm³",
                "Stan": "techniczny: Nieuszkodzony",
                "Skrzynia": "biegów: Manualna",
                "Kraj": "pochodzenia: Polska",
                "Moc": "silnika: 50 KM",
                "Napęd:": "Na przednie koła",
                "Kierownica:": "po lewej"
            }
        },
        {
            "title": "Peugeot 308SW 1.6 Benzyna 2009r Panorama Dach Hak Klima !",
            "price": "7 900 złdo negocjacji",
            "link": "https://www.olx.pl/oferta/peugeot-308sw-1-6-benzyna-2009r-panorama-dach-hak-klima-CID5-ID15cEmW.html",
            "description": "Witam sprzedam Peugeota 308 z silnikiem benzynowym o pojemności 1.6\n\nAuto jest z 2009 roku, 3 lata temu zostało sprowadzone ze Szwecji i od tamtej pory użytkowane przez jednego właściciela (pierwszy w kraju).\nWszystkie naprawy wykonywane były na bieżąco , olej wymieniany co 10tys km , w tym sprzęgło i rozrząd . Na chwilę obecną auto nie wymaga żadnego wkładu finansowego.\nSilnik suchy bez wycieków,nie dymi i ma moc . Oleju od wymiany do wymiany nie ubywa nawet kropli. \nZawieszenie bez luzów, auto dobrze się prowadzi , nie ściąga na boki i dobrze wybiera nierówności . \nTechnicznie bez zarzutów , wsiadać i jeździć . \nWizualnie auto wygląda tak jak na zdjęciach nie posiada oznak korozji , progi i podłoga również . \nŚrodek auta bez dziur i przetarć , ogólnie auto dobrze utrzymane . \nPeugeot zarejestrowany na 5 osób z możliwością rejestracji na 7 ( możliwość dołożenia foteli). \nAktualne ubezpiecznie oraz przegląd . \nWięcej informacji udzielę telefonicznie. \nZapraszam na oględziny auta oraz jazdę próbną.",
            "details": {
                "Numer": "VIN: VF34H5FXH9S154721",
                "Model:": "308",
                "Rok": "produkcji: 2009",
                "Paliwo:": "Benzyna",
                "Typ": "nadwozia: Kombi",
                "Przebieg:": "301 332 km",
                "Kolor:": "Inny kolor",
                "Poj.": "silnika: 1 600 cm³",
                "Stan": "techniczny: Nieuszkodzony",
                "Skrzynia": "biegów: Manualna",
                "Kraj": "pochodzenia: Szwecja",
                "Moc": "silnika: 150 KM",
                "Napęd:": "Na przednie koła",
                "Kierownica:": "po lewej"
            }
        },
        {
            "title": "Cinquecento 900 SX - proszę czytać opis przed kontaktem",
            "price": "8 500 zł",
            "link": "https://www.olx.pl/oferta/cinquecento-900-sx-prosze-czytac-opis-przed-kontaktem-CID5-ID15e6Eg.html",
            "description": "Proszę uważnie przeczytać opis, jest tutaj wiele informacji. Oględziny CC możliwe tylko w weekendy po wcześniejszym umówieniu.\n\nSprzedam ładne Cinquecento w wersji wyposażenia SX z silnikiem 900 z instalacją lpg drugiej generacji. Przebieg 128176 km.\nNa wyposażeniu:\n- elektryczne szyby,\n- centralny zamek,\n- dzielona kanapa z zagłówkami,\n- uchylne tylne szyby,\n- radio Sony.\nOd siebie dołożyłem zegary z Cinquecento Sporting do których przełożyłem wkład prędkościomierza z zegarów SXa, a na desce jest dodatkowy wskaźnik - docelowo miałabyć temperatura oleju. Zamontowany jest również stabilizator ze Sportinga, żeby Cinquecento nie bujało się w zakrętach. Przygotowana została instalacja pod dołożenie świateł przeciwmgielnych lub dalekosiężnych, wystarczy zamontować lampy.\nRobiłem go dla siebie pod Rajd Koguta, ale właśnie kupiłem inny egzemplarz z klimatyzacją więc dwa do szczęścia mi nie potrzebne.\nW cieniasie został wykonany remont blacharski przez poprzedniego właściciela, ale z racji, że użytkował go na co dzień przez cały rok to na progach przy łączeniu z podłogą pojawiły się zacieki rdzy. Wystarczy to zeszlifować, nałożyć np. Rstop i dać czarny baranek na całe progi, żeby było jak w oryginale. Niestety maska została wymieniona na współczesny zamiennik i krótko mówiąc zgniła od środka. Poza tym został cały polakierowany z zewnątrz na oryginalny kolor. Podszybia całe, nadkola wewnętrzne tylne również wymienione i polakierowane. Na dachu nałożona jest biała folia.\nJeżeli chodzi o mechanikę to już większość rzeczy robiłem sam lub u zaufanego mechanika:\n- cały silnik z nowymi uszczelkami więc nic nie cieknie,\n- nowa poduszka silnika Febi,\n- nowy olej, filtr oleju, pasek klinowy\n- nowy rozrząd,\n- nowy termostat i czujnik temperatury do wskaźnika na zegarach,\n- nowy płyn chłodniczy,\n- nowy akumulator,\n- nowy tłumik środkowy,\n- nowa linka sprzęgła i prędkościomierza,\nI pewnie coś jeszcze, ale w tym momencie nie przychodzi mi do głowy.\nZostała do wymiany już tylko pompa wody, bo ma za mały przepływ na wolnych obrotach i silnik łapie temperaturę.\nHamulców nie ruszałem, uważam że są dobre.\nInstalacja lpg po serwisie, wyregulowana, wymienione filtry, naprawione przewody, bo robiło się zwarcie, butla ważna jeszcze kilka lat.\nDo Cinquecento dodaje parę rzeczy do wyposażenia:\n- lusterko wewnętrzne, obecne ma pęknięte szkło,\n- nowe kratki od głośników,\n- pasy na tył zwijane,\n- nowe lampy z czarnym środkiem Depo z silniczkami od Sportinga,\ni parę dodatkowych pierdół.\nNa fotelach były założone pokrowce, ale fotel kierowcy jest podarty, fotele również do przeprania.\nObecnie założone są felgi z poloneza z oponami Nexen Nblue 155/65 r13 rocznik 2020, beżnik 7mm.\nDaję również komplet stalowych felg z oponami zimowymi Barum Polaris 5 145/70 r13 z 2021 roku, bieżnik 6,5-7mm.\nPrzegląd ważny do 15.05.2025 a ubezpieczenie 04.10.2025",
            "details": {
                "Model:": "Cinquecento",
                "Rok": "produkcji: 1996",
                "Paliwo:": "Benzyna",
                "Typ": "nadwozia: Hatchback",
                "Przebieg:": "128 176 km",
                "Kolor:": "Niebieski",
                "Poj.": "silnika: 900 cm³",
                "Stan": "techniczny: Nieuszkodzony",
                "Skrzynia": "biegów: Manualna"
            }
        },
        {
            "title": "Audi A6 C5 2.4 Benzyna + LPG | Automat",
            "price": "9 900 złdo negocjacji",
            "link": "https://www.olx.pl/oferta/audi-a6-c5-2-4-benzyna-lpg-automat-CID5-ID15a4Iw.html",
            "description": "Sprzedam Audi A6 C5 z 2000 roku z niezawodnym i dynamicznym silnikiem 2.4 (121 kW), który doskonale współpracuje z instalacją gazową LPG – oszczędna jazda bez utraty mocy! Automatyczna skrzynia biegów zapewnia komfort zarówno w mieście, jak i na trasie.\n\nPrzebieg: 270 000 km\nRodzaj paliwa: Benzyna + LPG\nBadanie techniczne ważne do: 25.05.2025 (możliwość wcześniejszego wykonania)\nUbezpieczenie OC ważne do: 09.2025\nInstalacja LPG: Wymieniony reduktor gazowy\nWymienione części: Nowe wtryski, świeży olej\n Wyposażenie:\nTkaninowa tapicerka \nElektrycznie sterowane lusterka\nPodgrzewane fotele – komfort w zimie!\nSprawna klimatyzacja\nAluminiowe felgi (Alufelgi)\n\nDodatkowo:\n Komplet nowych opon – letnie i zimowe!\n Samochód w pełni sprawny\n Gotowy do jazdy bez dodatkowych inwestycji\n\nAuto jest zadbane, w dobrym stanie technicznym i idealnie nadaje się zarówno na długie trasy, jak i do jazdy po mieście.",
            "details": {
                "Numer": "VIN: WAUZZZ4BZ1N050530",
                "Model:": "A6",
                "Rok": "produkcji: 2000",
                "Paliwo:": "LPG",
                "Typ": "nadwozia: Sedan",
                "Przebieg:": "270 000 km",
                "Kolor:": "Niebieski",
                "Poj.": "silnika: 2 393 cm³",
                "Stan": "techniczny: Nieuszkodzony",
                "Skrzynia": "biegów: Automatyczna",
                "Kraj": "pochodzenia: Niemcy",
                "Moc": "silnika: 121 KM",
                "Napęd:": "Na przednie koła",
                "Kierownica:": "po lewej"
            }
        },
        {
            "title": "Fiat Panda 1,2 benzyna + Gaz LPG * KLIMA * bez rdzy * tylko 114 tys km",
            "price": "9 900 zł",
            "link": "https://www.olx.pl/oferta/fiat-panda-1-2-benzyna-gaz-lpg-klima-bez-rdzy-tylko-114-tys-km-CID5-ID14IZbu.html",
            "description": "Do sprzedania posiadam bardzo ładnego Fiata Pandę sprowadzonego z Niemiec. Samochód posiada instalację gazową LPG. Silnik pracuje prawidłowo na obydwu paliwach. Blacharsko w bardzo dobrym stanie. Bez rdzy, rys, wgniotek. Środek zadbany - pod pokrowcami ładna niezniszczona tapicerka. Posiada klimatyzację, elektryczne szyby, wspomaganie kierownicy z funkcją CITY, ABS, Radio, 2 kluczyki. Ładne opony wielosezonowe. \nZapraszam do oglądania.",
            "details": {
                "Model:": "Panda",
                "Rok": "produkcji: 2007",
                "Paliwo:": "LPG",
                "Typ": "nadwozia: Hatchback",
                "Przebieg:": "114 000 km",
                "Kolor:": "Niebieski",
                "Poj.": "silnika: 1 242 cm³",
                "Stan": "techniczny: Nieuszkodzony",
                "Skrzynia": "biegów: Manualna",
                "Kraj": "pochodzenia: Niemcy",
                "Moc": "silnika: 60 KM",
                "Kierownica:": "po lewej"
            }
        },
        {
            "title": "Volvo S60 2.4 benzyna automat",
            "price": "8 400 złdo negocjacji",
            "link": "https://www.olx.pl/oferta/volvo-s60-2-4-benzyna-automat-CID5-ID156KVQ.html",
            "description": "Volvo S60 2.4 benzyna z gazem CNG  140 koni z automatyczną skrzynią biegów przebieg 199000 kilometrów udokumentowany ,silnik skrzynia zawieszenie pracują bardzo dobrze auto bezwypadkowe . Więcej informacji pod telefonem",
            "details": {
                "Numer": "VIN: Yv1hvxxxxxxxxxxxx",
                "Model:": "S60",
                "Rok": "produkcji: 2005",
                "Paliwo:": "Benzyna",
                "Typ": "nadwozia: Sedan",
                "Przebieg:": "199 000 km",
                "Kolor:": "Inny kolor",
                "Poj.": "silnika: 2 435 cm³",
                "Stan": "techniczny: Nieuszkodzony",
                "Skrzynia": "biegów: Automatyczna",
                "Kraj": "pochodzenia: Włochy",
                "Moc": "silnika: 140 KM",
                "Napęd:": "Na przednie koła",
                "Kierownica:": "po lewej"
            }
        },
        {
            "title": "Chrysler Voyager",
            "price": "10 000 złdo negocjacji",
            "link": "https://www.olx.pl/oferta/chrysler-voyager-CID5-ID15egCE.html",
            "description": "Witam. Sprzedam Chrysler Voyager IV 3.3 LPG 2xbutla w schowkach, 8 m-cy temu wymienione tarcze przód klocki amortyzatory, 2 lata temu robione głowice, olej w skrzyni co 30tys, w silniku co 10tys. Alufelgi lato, zima stal.\nProszę dzwonić po południu.",
            "details": {
                "Model:": "Grand Voyager",
                "Rok": "produkcji: 2005",
                "Paliwo:": "LPG",
                "Typ": "nadwozia: Minivan",
                "Przebieg:": "381 000 km",
                "Kolor:": "Zielony",
                "Stan": "techniczny: Nieuszkodzony",
                "Skrzynia": "biegów: Automatyczna",
                "Kraj": "pochodzenia: Dania",
                "Moc": "silnika: 180 KM",
                "Napęd:": "Na przednie koła",
                "Kierownica:": "po lewej"
            }
        },
        {
            "title": "Mercedes Benz E220 cdi",
            "price": "9 999 złdo negocjacji",
            "link": "https://www.olx.pl/oferta/mercedes-benz-e220-cdi-CID5-ID15aXQt.html",
            "description": "Sprzedam mercedes w210 e220cdi.Stan techniczny bdb silnik skrzynia biegów zawieszenie pracują wzorowo,brak wycieków.Środek zadbany wszystko działa.Auto bez korozji.Więcej informacji lub zdjęć proszę o kontakt telefoniczny.",
            "details": {
                "Numer": "VIN: WDB2100061B238233",
                "Model:": "E Klasa",
                "Rok": "produkcji: 2000",
                "Paliwo:": "Diesel",
                "Typ": "nadwozia: Sedan",
                "Przebieg:": "400 000 km",
                "Kolor:": "Inny kolor",
                "Poj.": "silnika: 2 151 cm³",
                "Stan": "techniczny: Nieuszkodzony",
                "Skrzynia": "biegów: Automatyczna",
                "Moc": "silnika: 143 KM",
                "Napęd:": "Na tylne koła",
                "Kierownica:": "po lewej"
            }
        },
        {
            "title": "Opel CORSA 1.4 benzyna GAZ Klimatyzacja",
            "price": "7 600 zł",
            "link": "https://www.olx.pl/oferta/opel-corsa-1-4-benzyna-gaz-klimatyzacja-CID5-ID14FPuG.html",
            "description": "Witam \nSprzedam OPEL CORSA 1.4( 90) z\n2008 z instalacją gazową z przebiegiem 235000 . \nJest najlepsza jednostka napędową w Corsie, jest dynamiczna a zarazem oszczędna bardzo dobrze pracuje na benzynie jak i na GAZIE  . Auto zostało sprowadzone w 2014 roku i do tej pory miało tylko  2 właścicieli . Auto po względem technicznym prezentuje się dobrze silnik pracuje cicho i równo niema żadnych wycieków,sprzęgło w dobrym stanie skrzynia biegów pracuje dobrze. Zawiesznie sztywne bez jakichkolwiek stuków czy luzów. Wizualnie prezentuje dobrze bez większych oznak korozji rys czy wgniotek. \nŚrodek utrzymany w dobrym stanie wszystkie podzespoły Elektryczne działają prawidłowo. \n\nWyposażenie to min.\n*KLIMATYZACJA \n*WSPOMAGANIE KIEROWNICY \n*ELEKTRYCZNE SZYBY \n*ELEKTRYCZNE LUSTERKA \n*RADIO CD \n*PODUSZKI POWIETRZNE \n*HALOGENY\n*CENTRALNY ZAMEK \n\nZapraszam cena do negocjacji",
            "details": {
                "Model:": "Corsa",
                "Rok": "produkcji: 2008",
                "Paliwo:": "LPG",
                "Typ": "nadwozia: Hatchback",
                "Przebieg:": "235 000 km",
                "Kolor:": "Srebrny",
                "Poj.": "silnika: 1 390 cm³",
                "Stan": "techniczny: Nieuszkodzony",
                "Skrzynia": "biegów: Manualna",
                "Moc": "silnika: 90 KM"
            }
        },
        {
            "title": "Alfa Romeo GT 1.9 JTD 150KM 2008r. (Bogata wersja)",
            "price": "3 500 złdo negocjacji",
            "link": "https://www.olx.pl/oferta/alfa-romeo-gt-1-9-jtd-150km-2008r-bogata-wersja-CID5-ID15bVm7.html",
            "description": "Na sprzedaż Alfa Romeo GT z 2008r. 1.9 JTD 150KM\nAuto sprzedaje w CAŁOŚCI ale ze względów na sytuację blacharsko-lakierniczą z przeznaczeniem raczej na części(stąd ta cena). Elementy oklejone folią i progi nadają się do całkowitej renowacji.\nPod kątem mechnicznym nie ma problemów, silnik o skrzynia działają prawidłowo, wszystkie naprawy robione na bieżąco. Turbina regenerowana 3lata temu, zeszłej jesieni wymieniane olej i filtry.\nPrzebieg ok. 258 000km\nCena 3500zl do negocjacji.\n\nAlfa posiada kilka ciekawych dodatków: sportową kierownicę, radio multimedialne, kamerkę cofania, prawie nowy lewy reflektor (ma 5 lat) i wiele innych.\nDo auta dorzucam również opony letnie, suboofer i wszystkie dodatkowe części które posiadam.\n\nZapraszam osoby zdecydowane na oglądanie, jest to dobra baza pod jakiś projekt lub na sam zarobek z części. Auto jest sprawne i można nim spokojnie wracać na kołach. Z tego co trzeba zrobić na teraz to jedynie wymienić łożysko koła tylnego lewego (szumi podczas jazdy) i linkę ręcznego. OC i przegląd ważne ale się szybko kończą.\n\nOsoby zainteresowne proszę o kontakt:\n7 2 4  1 3 0  7 0 8",
            "details": {
                "Model:": "GT",
                "Rok": "produkcji: 2008",
                "Paliwo:": "Diesel",
                "Typ": "nadwozia: Coupe",
                "Przebieg:": "258 000 km",
                "Kolor:": "Czarny",
                "Poj.": "silnika: 1 910 cm³",
                "Stan": "techniczny: Nieuszkodzony",
                "Skrzynia": "biegów: Manualna",
                "Kraj": "pochodzenia: Włochy",
                "Moc": "silnika: 150 KM",
                "Napęd:": "Na przednie koła",
                "Kierownica:": "po lewej"
            }
        },
        {
            "title": "Autokomis TopCar! Skoda Fabia 1.4 Diesel/2008 Rok/Licenzia Taxi/Okazja",
            "price": "4 490 złdo negocjacji",
            "link": "https://www.olx.pl/oferta/autokomis-topcar-skoda-fabia-1-4-diesel-2008-rok-licenzia-taxi-okazja-CID5-ID15brXr.html",
            "description": "Autokomis TopCar Ul. Poznańska 308 Ożarów Mazowiecki \n\nMOŻLIWOŚĆ ZOSTAWIENIA \nAUTA W ROZLICZENIU !\n\nTAK ŻE OFERUJEMY USŁUGĘ DOSTARCZENIA AUTA POD DOM \n\nWitam wszystkich, na sprzedaż leci piękna i niezawodna Skoda Fabia wyprodukowana w 2008 Roku z najlepszym niezawodnym silnikiem 1.4 Diesel, autko jest zadbane i serwisowane zawsze na czas w tej chwili jest w 100% sprawne i nie potrzebuje wkładu finansowego, OC i PT jest aktualne tak że śmiało można wracać na kołach \n\nZ wyposażenia to:\n\n- Elektryczne 4 szyby \n- centralny zamek\n- podgrzewana tylna szyba\n- System ABS + EBD + EBA\n- wspomaganie kierownicy\n- Elektroniczny zegar\n- Elektroniczny termometr temp zewnetrznej\n- Kierownica regulowana w dwoch plazczyznach\n- Reczna regulacja wysokosci reflektorow\n- Komputer pokladowy obliczajacy srednie/chwilowe spalanie, zasieg auta itd\n- podgrzewane lusterka\n- elektrycznie sterowane szyby (przod+tyl)\n- dwustrefowy klimatronik\n\nAutko jest w dobrym stanie zadbane i bardzo przyjemne w użytkowaniu \n\nCHĘTNIE ZAMIENIMY! \n\nRÓWNIEŻ SKUPUJEMY AUTA ZA GOTÓWKĘ ! \n\nZapraszamy na oglądanie i jazdę próbną \n\nAdres ul. Poznańska 308, Ożarów Mazowiecki \n\nOtwarte jest 7 Dni w tygodni\n\nW dni świąteczne również pracujemy \n\nOd 10:00 do 20:00\n\nWystawiam fakturę VAT-MARŻA, kupujący jest zwolniony z opłaty skarbowej!\n\nNiniejsze ogłoszenie jest wyłącznie informacją handlową i nie stanowi oferty w myśl art. 66, §1.Kodeksu Cywilnego. Sprzedający nie odpowiada za ewentualne błędy lub nieaktualność ogłoszenia.",
            "details": {
                "Model:": "Fabia",
                "Rok": "produkcji: 2008",
                "Paliwo:": "Diesel",
                "Typ": "nadwozia: Kombi",
                "Przebieg:": "300 000 km",
                "Kolor:": "Inny kolor",
                "Poj.": "silnika: 1 400 cm³",
                "Stan": "techniczny: Nieuszkodzony",
                "Skrzynia": "biegów: Manualna",
                "Napęd:": "Na przednie koła",
                "Kierownica:": "po lewej"
            }
        },
        {
            "title": "Opel Signum 1.9 150KM Skrzynia 6 biegów Czujniki Parkowania",
            "price": "3 900 złdo negocjacji",
            "link": "https://www.olx.pl/oferta/opel-signum-1-9-150km-skrzynia-6-biegow-czujniki-parkowania-CID5-ID14p9ju.html",
            "description": "Witam mam na sprzedaż auto marki Opel Signum wyprodukowanego w 2004r \nAuto jest w dobrym stanie technicznym (przy dodaniu gazu kopci na czarno-prawdopodobnie ktorys wtrysk do wymiany)\nŻadnych błędów nie ma na desce rozdzielczej \nWizualnie w bardzo dobrym stanie jak na 20 letnie auto (bez korozji)\nŚrodek auta w bardzo dobrym stanie \nProgi oraz podłoga w dobrym stanie \n\nOC I przegląd aktualne do listopada 2025r \n\nCena 3900zl \nWięcej informacji na priv lub 788x800x159",
            "details": {
                "Model:": "Signum",
                "Rok": "produkcji: 2004",
                "Paliwo:": "Diesel",
                "Typ": "nadwozia: Hatchback",
                "Przebieg:": "288 000 km",
                "Kolor:": "Czarny",
                "Poj.": "silnika: 1 900 cm³",
                "Stan": "techniczny: Nieuszkodzony",
                "Skrzynia": "biegów: Manualna",
                "Kraj": "pochodzenia: Niemcy",
                "Moc": "silnika: 150 KM"
            }
        },
        {
            "title": "Fiat Panda # Tylko 144.000 km # Nowy Rozrząd # Wspomaganie # Elektryka",
            "price": "7 900 złdo negocjacji",
            "link": "https://www.olx.pl/oferta/fiat-panda-tylko-144-000-km-nowy-rozrzad-wspomaganie-elektryka-CID5-ID14wgtN.html",
            "description": "Opis samochodu niżej.\n- - - - - - - - - - - - - - - - - - - - - - - - - - -\n\nSkupujemy Auta WSZYSTKICH MAREK za GOTÓWKĘ od 1.000 do 50.000 złotych u nas na miejscu bądź z dojazdem do klienta do 100 km od Radomia ! Więcej informacji udzielimy telefonicznie.\n- - - - - - - - - - - - - - - - - - - - - - - - - - -\n\nPrzyjmiemy każde auto w rozliczeniu, droższe oraz tańsze.\n- - - - - - - - - - - - - - - - - - - - - - - - - - -\n\nWitam, mam do sprzedania FIAT PANDA z 2005 roku, pierwsza rejestracja w 2006. KOMPLETNY ROZRZĄD WYMIENIONY przy przebiegu 129.000 km - Potwierdzony !! Samochód na Polskich tablicach, zarejestrowany i ubezpieczony - zaraz po zakupie można się nim normalnie poruszać bez ryzyka wysokiego mandatu ! FIATA napędza niezawodny silnik 1.1 BENZYNA o mocy 54 który rewelacyjnie się spisuje zarówno w mieście jak i na trasie ciesząc się niskim spalaniem w granicach 6 L PB. Samochód wyposażony m.in w: El. szyby, Wspomaganie Kierownicy + CITY,  Centralny Zamek, AIRBAG, Radio, itd. Wnętrze Bardzo czyste i zadbane, nic nie poprzecierane. Z zewnątrz w Bardzo dobrym stanie, bez rys , korozji brak. Technicznie stan bardzo dobry silnik pracuje równo i cicho, nie szarpie, skrzynia również w bardzo dobrym stanie, zawieszenie sztywne nie wybite. Możliwość sprawdzenia na dowolnej stacji diagnostycznej. Na auto wystawiam fakturę VAT marże dzięki czemu kupujący nie płaci opłaty skarbowej ok 200 złotych.. Polecam\n\n_ _ _ _ _ _ _ _ _ _ _ _ _ _ _ _ _ _ _ _ _ _ _ _ _ _\n\nOC i Przegląd AKTUALNE, Samochodem można śmiało się poruszać..\n\n- - - Każdy Przebieg potwierdzamy pisemnie na fakturze - - -\n\n# # # Możliwość pozostawienia auta w rozliczeniu na miejscu - przyjmujemy każde auto # # #\n\n_ _ _ _ _ _ _ _ _ _ _ _ _ _ _ _ _ _ _ _ _ _ _ _ _ _\n\nAUTO HANDEL Mateusz Urbaniak\n\nAdres 26-600 Radom ul. Warszawska 190\n\nGodziny Otwarcia:\n\nPoniedziałek - Piątek : 10:00 - 16:00\n\nSobota : 10:00 - 15:00\n\nNiedziela : 10:30 - 14:00\n\nMożliwość uzgodnienia innej godziny oględzin auta po wcześniejszym ustaleniu telefonicznym\n\n_ _ _ _ _ _ _ _ _ _ _ _ _ _ _ _ _ _ _ _ _ _ _ _ _ _\n\nSkupujemy Auta WSZYSTKICH MAREK za GOTÓWKĘ od 1.000 do 50.000 złotych u nas na miejscu bądź z dojazdem do klienta do 100 km od Radomia ! Więcej informacji udzielimy telefonicznie.",
            "details": {
                "Numer": "VIN: ZFA16900000529753",
                "Model:": "Panda",
                "Rok": "produkcji: 2006",
                "Paliwo:": "Benzyna",
                "Typ": "nadwozia: Hatchback",
                "Przebieg:": "144 200 km",
                "Kolor:": "Inny kolor",
                "Poj.": "silnika: 1 100 cm³",
                "Stan": "techniczny: Nieuszkodzony",
                "Skrzynia": "biegów: Manualna",
                "Kraj": "pochodzenia: Polska",
                "Moc": "silnika: 54 KM",
                "Napęd:": "Na przednie koła",
                "Kierownica:": "po lewej"
            }
        },
        {
            "title": "Sprzedam auto pilnie",
            "price": "2 500 złdo negocjacji",
            "link": "https://www.olx.pl/oferta/sprzedam-auto-pilnie-CID5-ID15eh6r.html",
            "description": "samochód wygląda jak na zdjęciu.ja wróciłem do domu i samochód nie odpala silnik się kręci ale nie odpala.powiedziałem że instalacja ubezpieczenie do kwietnia przegląd techniczny do końca roku. Jeśli nie odbieram telefonu, napisz do mnie, że dzwoniłeś w sprawie samochodu.",
            "details": {
                "Model:": "Corsa",
                "Rok": "produkcji: 2004",
                "Paliwo:": "LPG",
                "Typ": "nadwozia: Hatchback",
                "Przebieg:": "236 879 km",
                "Kolor:": "Czerwony",
                "Poj.": "silnika: 1 199 cm³",
                "Stan": "techniczny: Uszkodzony",
                "Skrzynia": "biegów: Manualna"
            }
        },
        {
            "title": "Skoda Octavia II 1.9 TDI Niemcy 162tyś km",
            "price": "9 000 zł",
            "link": "https://www.olx.pl/oferta/skoda-octavia-ii-1-9-tdi-niemcy-162tys-km-CID5-ID15ehc0.html",
            "description": "Na sprzedaż Skoda Octavia II z 2004r. z pancernym i niezawodnym silnikiem 1.9 TDI. Auto zostało kupione w Niemieckim salonie/serwisie volkswagena z przebiegiem 162.000 km. Na wszystko posiadam papiery. Samochód w bardzo dobrym stanie, wizualnie jak widać, w pełni sprawne mechanicznie bez wkładu.  Założony komplet nowych błotników z przodu, wymieniony filtr paliwa, praktycznie nowe tarcze hamulcowe. \nKontakt telefoniczny 7.3.0.7.1.8.7.2.0 lub 5.0.2.0.7.9.2.1.7",
            "details": {
                "Model:": "Octavia",
                "Rok": "produkcji: 2004",
                "Paliwo:": "Diesel",
                "Typ": "nadwozia: Sedan",
                "Przebieg:": "162 000 km",
                "Kolor:": "Niebieski",
                "Poj.": "silnika: 1 900 cm³",
                "Stan": "techniczny: Nieuszkodzony",
                "Skrzynia": "biegów: Manualna",
                "Kraj": "pochodzenia: Niemcy",
                "Moc": "silnika: 105 KM",
                "Kierownica:": "po lewej"
            }
        },
        {
            "title": "Mazda 3 LPG 2006 Balck",
            "price": "6 500 zł",
            "link": "https://www.olx.pl/oferta/mazda-3-lpg-2006-balck-CID5-ID146IKt.html",
            "description": "Dzień dobry, sprzedaję swój samochód! Mazda 3 2006 2.0 benzyna/gaz. Wszystkie dokumenty są w porządku. ubezpieczenie do października, przegląd techniczny również do października. Samochód jest dobrze utrzymany i posiadany. Według dokumentów jestem właścicielem. Wszelkie pytania proszę kierować telefonicznie lub przez wiadomość, możliwa jest negocjacja, możliwa jest również zamiana.",
            "details": {
                "Model:": "3",
                "Rok": "produkcji: 2006",
                "Paliwo:": "LPG",
                "Typ": "nadwozia: Hatchback",
                "Przebieg:": "253 000 km",
                "Kolor:": "Czarny",
                "Poj.": "silnika: 2 000 cm³",
                "Stan": "techniczny: Nieuszkodzony",
                "Skrzynia": "biegów: Manualna",
                "Moc": "silnika: 150 KM"
            }
        },
        {
            "title": "CITROEN C3 Benzyna 135 719 Przebieg",
            "price": "6 500 zł",
            "link": "https://www.olx.pl/oferta/citroen-c3-benzyna-135-719-przebieg-CID5-ID15egOb.html",
            "description": "Sprzedam samochód marki Citroen C3\nBenzyna 1.4 75 km\nSamochodem jeździł, dziadek który przez ostatnie 8 lat użytkowania auta przejechał nim ok 10 tyś km.\nAuto nie wymaga żadnego wkładu finansowego.\nKlimatyzacja sprawna \nOpony letnie oraz zimowe w cenie \nBlacharsko auto nie wymaga żadnego wkładu finansowego.",
            "details": {
                "Model:": "C3",
                "Rok": "produkcji: 2003",
                "Paliwo:": "Benzyna",
                "Typ": "nadwozia: Sedan",
                "Przebieg:": "135 719 km",
                "Kolor:": "Niebieski",
                "Poj.": "silnika: 1 400 cm³",
                "Stan": "techniczny: Nieuszkodzony",
                "Skrzynia": "biegów: Manualna",
                "Kraj": "pochodzenia: Polska",
                "Moc": "silnika: 75 KM",
                "Napęd:": "Na przednie koła",
                "Kierownica:": "po lewej"
            }
        },
        {
            "title": "Sprzedam Opla Zafirę A",
            "price": "6 000 złdo negocjacji",
            "link": "https://www.olx.pl/oferta/sprzedam-opla-zafire-a-CID5-ID14ZeK2.html",
            "description": "Sprzedam Opla Zafirę A.\n1,8 benzyna plus gaz \nWersja 7 osobowa \nRok produkcji 2004\nPierwszy właściciel w Polsce. \nPierwsza rejestracja w Polsce 2016 r.\nGaz do 31.08.2026r. \nPrzegląd i OC ważne. \n5.1.5.9.3.7.4.3.5",
            "details": {
                "Model:": "Zafira",
                "Rok": "produkcji: 2004",
                "Paliwo:": "LPG",
                "Typ": "nadwozia: Minivan",
                "Przebieg:": "322 000 km",
                "Kolor:": "Niebieski",
                "Poj.": "silnika: 1 800 cm³",
                "Stan": "techniczny: Nieuszkodzony",
                "Skrzynia": "biegów: Manualna",
                "Kraj": "pochodzenia: Polska",
                "Moc": "silnika: 125 KM",
                "Napęd:": "Na przednie koła",
                "Kierownica:": "po lewej"
            }
        },
        {
            "title": "Opel Meriva A 2005 r. 1,8 benzyna LPG 125KM",
            "price": "5 300 zł",
            "link": "https://www.olx.pl/oferta/opel-meriva-a-2005-r-1-8-benzyna-lpg-125km-CID5-ID15egqS.html",
            "description": "Opel Meriva A\nRocznik 2005\nPrzebieg ok. 305000 km \nData pierwszej rejestracji w kraju 2016\nTermin homologacji zbiornika LPG - kwiecień 2026\nPrzegląd techniczny - lipiec 2025\nUbezpieczenie - do końca listopada 2025\nHak\nAlufelgi\n\nW ostatnim czasie wymienione dwie sprężyny z tyłu, przewody hamulcowe, sygnał dźwiękowy, naprawiony wydech. Ogólnie, gdy pojawiały się jakieś problemy to naprawiany na bieżąco (wymieniony alternator, stacyjka). \n\nSamochód sprawny, ale ma swoje lata więc jest trochę rdzy (prawe przednie drzwi), kilka przetarc, lewa przednia szyba przycina się. \n\nOgólnie samochód dobry, tani w utrzymaniu, bardzo dobry silnik, sporo miejsca - po złożeniu tylnich foteli bardzo duża przestrzeń ładunkowa.",
            "details": {
                "Model:": "Meriva",
                "Rok": "produkcji: 2005",
                "Paliwo:": "LPG",
                "Typ": "nadwozia: Minivan",
                "Przebieg:": "305 000 km",
                "Kolor:": "Srebrny",
                "Poj.": "silnika: 1 cm³",
                "Stan": "techniczny: Nieuszkodzony",
                "Skrzynia": "biegów: Manualna",
                "Moc": "silnika: 125 KM",
                "Napęd:": "Na przednie koła",
                "Kierownica:": "po lewej"
            }
        },
        {
            "title": "Ford Focus MK2 2008r",
            "price": "8 300 zł",
            "link": "https://www.olx.pl/oferta/ford-focus-mk2-2008r-CID5-ID15egic.html",
            "description": "Sprzedam Forda Focusa 1.6TDCi z 2008r W bardzo dobrym stanie \n\nWyposażenie:\n- 2 kluczyki\n- centralny zamek z pilota\n- elektryczne szyby przednie\n- klimatyzacja\n- ABS\n-koła zima\n\nTO: 2025-12-23\nCT: 2025-05-15",
            "details": {
                "Numer": "VIN: WF0PXCGCDP8A60723",
                "Model:": "Focus",
                "Rok": "produkcji: 2008",
                "Paliwo:": "Diesel",
                "Typ": "nadwozia: Hatchback",
                "Przebieg:": "293 093 km",
                "Kolor:": "Biały",
                "Poj.": "silnika: 1 600 cm³",
                "Stan": "techniczny: Nieuszkodzony",
                "Skrzynia": "biegów: Manualna",
                "Moc": "silnika: 90 KM",
                "Napęd:": "Na przednie koła",
                "Kierownica:": "po lewej"
            }
        },
        {
            "title": "Ford S-Max 2.0 diesel 2006r",
            "price": "9 500 złdo negocjacji",
            "link": "https://www.olx.pl/oferta/ford-s-max-2-0-diesel-2006r-CID5-ID13LR4O.html",
            "description": "Witam. Sprzedam Forda S-Maxa, samochód w ciągłej eksploatacji ma kilka mankamentow i plusów( nowe zawieszenie tył oraz nowa podgrzewana szyba przednia). Zapraszam do zakupu",
            "details": {
                "Model:": "S-Max",
                "Rok": "produkcji: 2006",
                "Paliwo:": "Diesel",
                "Typ": "nadwozia: Minivan",
                "Przebieg:": "335 000 km",
                "Kolor:": "Zielony",
                "Poj.": "silnika: 1 997 cm³",
                "Stan": "techniczny: Nieuszkodzony",
                "Skrzynia": "biegów: Manualna",
                "Moc": "silnika: 130 KM",
                "Napęd:": "Na przednie koła",
                "Kierownica:": "po lewej"
            }
        },
        {
            "title": "Autokomis TopCar! Ford Ka 1.6 Benzyna/Kabriolet/Bdstan/Maly przebieg/",
            "price": "5 490 złdo negocjacji",
            "link": "https://www.olx.pl/oferta/autokomis-topcar-ford-ka-1-6-benzyna-kabriolet-bdstan-maly-przebieg-CID5-ID14Qrsl.html",
            "description": "Autokomis TopCar Ul. Poznańska 308 Ożarów Mazowiecki \n\nMOŻLIWOŚĆ ZOSTAWIENIA \nAUTA W ROZLICZENIU !\n\nTAK ŻE OFERUJEMY USŁUGĘ DOSTARCZENIA AUTA POD DOM \n\nWitam wszystkich, na sprzedaż leci piękny i niezawodny Ford Ka wyprodukowany w 2004 Roku z najlepszym niezawodnym silnikiem 1.6 Benzyna, autko jest zadbane i serwisowane zawsze na czas w tej chwili jest w 100% sprawne i nie potrzebuje wkładu finansowego, OC i PT jest aktualne tak że śmiało można wracać na kołach \n\nZ wyposażenia to:\n\n- Elektryczne szyby \n- centralny zamek\n- podgrzewana tylna szyba\n- System ABS + EBD\n- wspomaganie kierownicy\n- Elektroniczny zegar\n- Elektroniczny termometr temp zewnetrznej\n- Kierownica regulowana w dwoch plazczyznach\n- Reczna regulacja wysokosci reflektorow\n\nAutko jest w dobrym stanie zadbane i bardzo przyjemne w użytkowaniu \n\nCHĘTNIE ZAMIENIMY! \n\nRÓWNIEŻ SKUPUJEMY AUTA ZA GOTÓWKĘ ! \n\nZapraszamy na oglądanie i jazdę próbną \n\nAdres ul. Poznańska 308, Ożarów Mazowiecki \n\nOtwarte jest 7 Dni w tygodni\n\nW dni świąteczne również pracujemy \n\nOd 10:00 do 20:00\n\nWystawiam fakturę VAT-MARŻA, kupujący jest zwolniony z opłaty skarbowej!\n\nNiniejsze ogłoszenie jest wyłącznie informacją handlową i nie stanowi oferty w myśl art. 66, §1.Kodeksu Cywilnego. Sprzedający nie odpowiada za ewentualne błędy lub nieaktualność ogłoszenia.",
            "details": {
                "Model:": "KA",
                "Rok": "produkcji: 2004",
                "Paliwo:": "Benzyna",
                "Typ": "nadwozia: Kabriolet",
                "Przebieg:": "168 000 km",
                "Kolor:": "Czarny",
                "Poj.": "silnika: 1 600 cm³",
                "Stan": "techniczny: Nieuszkodzony",
                "Skrzynia": "biegów: Manualna",
                "Napęd:": "Na przednie koła",
                "Kierownica:": "po lewej"
            }
        },
        {
            "title": "Opel Astra- sprzedam",
            "price": "9 500 złdo negocjacji",
            "link": "https://www.olx.pl/oferta/opel-astra-sprzedam-CID5-ID15egxd.html",
            "description": "Opel Astra \n1.4\n2009r.\n230 tys.\nRegularnie serwisowany \n2 komplety opon ( lato, zima)\nKlimatyzacja \nCena: 9500 zł ( do negocjacji)\nTel. 50*******15\nZapraszam!",
            "details": {
                "Model:": "Astra",
                "Rok": "produkcji: 2009",
                "Paliwo:": "Benzyna",
                "Typ": "nadwozia: Hatchback",
                "Przebieg:": "230 km",
                "Kolor:": "Niebieski",
                "Poj.": "silnika: 14 cm³",
                "Stan": "techniczny: Nieuszkodzony",
                "Skrzynia": "biegów: Manualna",
                "Kraj": "pochodzenia: Niemcy",
                "Napęd:": "Na przednie koła",
                "Kierownica:": "po lewej"
            }
        },
        {
            "title": "Toyota Avensis*1.8 benzyna*zadbana.",
            "price": "9 200 złdo negocjacji",
            "link": "https://www.olx.pl/oferta/toyota-avensis1-8-benzynazadbana-CID5-ID15egbV.html",
            "description": "Sprzedam Toyote  Avensis z dynamicznym silnikiem 1.8 w benzynie.\n\nSamochód prezentuje się Znakomicie, ciemny kolor, oryginalna alufelga, przyciemnione szyby, pakiet chrom wszystko to sprawia że samochód przyciąga WZROK.\n\nSilnik pracuje bardzo dobrze, samochód prowadzi się komfortowo .\n\nWygodny , przestronny i ekonomiczny .\n\nRozrząd n łańcuszku , po wymianie oleju.\n\nLakier utrzymany w świetnym stanie , bez oznak korozji.\n\nWnętrze czyste i zadbane , wygodne .\n\nŚwieżo zrobione opłaty OC ważne na kolejny rok.\n\nWyposażenie \n\n* Wspomaganie kierownicy \n\n* Centralny zamek \n\n* Elektryczne szyby \n\n * Elektryczne lusterka \n\n *Przyciemnione szyby \n\n* Pakiet chrom \n\n* Radio\n\n* Klimatyzacja ( sprawna )\n\n* Grzane fotele \n\n* 3 kluczyki\n\n* ABS\n\n* Itd...\n\nWięcej informacji udzielę telefonicznie.\n\nZapraszam do obejrzenia i na jazdę próbną.\n\nAuto stoi na bardzo ładnych felgach z ładnymi letnimi oponami .",
            "details": {
                "Model:": "Avensis",
                "Rok": "produkcji: 2004",
                "Paliwo:": "Benzyna",
                "Typ": "nadwozia: Kombi",
                "Przebieg:": "1 km",
                "Kolor:": "Czarny",
                "Poj.": "silnika: 1 800 cm³",
                "Stan": "techniczny: Nieuszkodzony",
                "Skrzynia": "biegów: Manualna",
                "Kierownica:": "po lewej"
            }
        },
        {
            "title": "Mazda 2 HAK  2004r SUPER STAN 1.4 80kM zapraszam Płońsk",
            "price": "3 100 zł",
            "link": "https://www.olx.pl/oferta/mazda-2-hak-2004r-super-stan-1-4-80km-zapraszam-plonsk-CID5-ID15eg9g.html",
            "description": "Witam wszystkich oglądających naszą mazdę...\n1.4 16v \n80kM\n2004r.\nAuto w świetnym stanie technicznym, na bieżąco serwisowane, nie ma do czego się przyczepić, wszystko działa.\nSilnik nie dymi i ładnie przyspiesza, \nSkrzynia i sprzęgło działa jak należy.\nZawieszenie idealne, zero luzów, żadnych puków, prowadzi się jak \"po sznurku\".\nBogate wyposażenie, hak wbity w dowód, 4 elektryczne szyby, elektryczne lusterka, sterowanie radiem z kierownicy itd...\nPodłoga ani grama rdzy, \nNadwozie jak na fotografiach, bardzo dobry stan jak na ten rocznik, nosi normalne ślady użytkowania.\nOC 07.2025\nBT 09.2025\nW razie pytań proszę dzwonić.\nNie odpisuje bo nie mam czasu na bezsensowną wymianę zdań z \"tyłko...zawracaczami\" \nZapraszam",
            "details": {
                "Model:": "2",
                "Rok": "produkcji: 2004",
                "Paliwo:": "Benzyna",
                "Typ": "nadwozia: Hatchback",
                "Przebieg:": "243 000 km",
                "Kolor:": "Inny kolor",
                "Poj.": "silnika: 1 388 cm³",
                "Stan": "techniczny: Nieuszkodzony",
                "Skrzynia": "biegów: Manualna",
                "Moc": "silnika: 80 KM",
                "Napęd:": "Na przednie koła"
            }
        },
        {
            "title": "Toyota Yaris I 2001 1.0 B+LPG",
            "price": "4 200 złdo negocjacji",
            "link": "https://www.olx.pl/oferta/toyota-yaris-i-2001-1-0-b-lpg-CID5-ID15efLy.html",
            "description": "Toyota Yaris 1 2002\nSilnik 1.0 benzyna + LPG instalacja STAGA\nAkumulator kręci nawet po kilku dniach w mroźne dni, odpala bez problemu, przełącza się na gaz.\nTeraz na prawie nowych oponach, wysoki bierznik, guma mięciutka, trzyma się jak zły \nW tamtym roku wykonana konserwacja podwozia i profili woskiem, nie jest lepiony jakimś bitexem aby tylko przykryć dziury, ten sposób konserwacji pozwala ocenić stan podwozia, belki, mocowania, podłużnic itp. przed konserwacją korozja która już była została potraktowana neutralizatorem a po tygodniu poszła konserwacja.\nWymienione zostały przy okazji tłoczki hamulcowe tył i poprowadzone do nich nowe przewody.\nZ zewnątrz lakier zewnętrzny tzw. standardowo się łuszczy, jest kilka miejsc do zrobienia zaprawek jak widać na zdjęciach.\nLokalizacja Warszawa Białołęka \nJak masz pytania dzwoń po 16, ogłoszenie wystawiam również na grupach.",
            "details": {
                "Model:": "Yaris",
                "Rok": "produkcji: 2001",
                "Paliwo:": "LPG",
                "Typ": "nadwozia: Hatchback",
                "Przebieg:": "263 800 km",
                "Kolor:": "Czerwony",
                "Poj.": "silnika: 998 cm³",
                "Stan": "techniczny: Nieuszkodzony",
                "Skrzynia": "biegów: Manualna",
                "Kraj": "pochodzenia: Polska",
                "Moc": "silnika: 65 KM",
                "Napęd:": "Na przednie koła",
                "Kierownica:": "po lewej"
            }
        },
        {
            "title": "Ford Mondeo Mk3 Długie Opłaty!",
            "price": "4 200 złdo negocjacji",
            "link": "https://www.olx.pl/oferta/ford-mondeo-mk3-dlugie-oplaty-CID5-ID15eg9N.html",
            "description": "Posiadam do sprzedaży Ford Mondeo Mk3 TDDI 2.0   115km\nPrzegląd do 31.01.2026\nUbezpiecznie do 13.02.2026\nAuto sprawne, gotowe do jazdy \nStoi na felgach aluminiowych 16’ -oponach zimowych , dodatkowo komplet letnich opon. \nStan jak na zdjęciach\nPodłoga i progi robione w 2024 roku. \nPosiada kilka obtarć parkingowych\nPo więcej informacji zapraszam pod numerem telefonu.",
            "details": {
                "Model:": "Mondeo",
                "Rok": "produkcji: 2002",
                "Paliwo:": "Diesel",
                "Typ": "nadwozia: Hatchback",
                "Przebieg:": "268 000 km",
                "Kolor:": "Czarny",
                "Poj.": "silnika: 1 998 cm³",
                "Stan": "techniczny: Nieuszkodzony",
                "Skrzynia": "biegów: Manualna",
                "Moc": "silnika: 115 KM",
                "Napęd:": "Na przednie koła",
                "Kierownica:": "po lewej"
            }
        },
        {
            "title": "Citroen C8 2.2 HDI",
            "price": "6 500 zł",
            "link": "https://www.olx.pl/oferta/citroen-c8-2-2-hdi-CID5-ID14GH0p.html",
            "description": "Sprzedam Citroena C8.  Rok produkcji 2004, z salonu w Polsce wyjechał w 2005r.\n5 miejsc siedzących. Posiada hak. \nJestem drugim właścicielem auta, przez wiele lat służył naszej rodzinie. Jest bardzo wygodny i pojemny.\nAuto jest bezwypadkowe, w bardzo dobrym stanie, zadbany.\nSprzedaję, bo zakupione zostało inne auto.\n\nPolecam!",
            "details": {
                "Numer": "VIN: VF7EBRHWB13182491",
                "Model:": "C8",
                "Rok": "produkcji: 2004",
                "Paliwo:": "Diesel",
                "Typ": "nadwozia: Minivan",
                "Przebieg:": "320 000 km",
                "Kolor:": "Szary",
                "Poj.": "silnika: 2 cm³",
                "Stan": "techniczny: Nieuszkodzony",
                "Skrzynia": "biegów: Manualna",
                "Kraj": "pochodzenia: Polska",
                "Napęd:": "Na przednie koła",
                "Kierownica:": "po lewej"
            }
        },
        {
            "title": "Ford Focus MK3 lift 1.0 benzyna kombi, niski przebieg",
            "price": "9 700 złdo negocjacji",
            "link": "https://www.olx.pl/oferta/ford-focus-mk3-lift-1-0-benzyna-kombi-niski-przebieg-CID5-ID14WeC8.html",
            "description": "Ford Focus MK3 po lifcie w stanie uszkodzonym jak na zdjęciach. Do wymiany pas przedni, chłodnice, kokpit, maska, lampy. Podłużnice i szyba, nie naruszone. Czysty zadbany",
            "details": {
                "Model:": "Focus",
                "Rok": "produkcji: 2015",
                "Paliwo:": "Benzyna",
                "Typ": "nadwozia: Kombi",
                "Przebieg:": "120 km",
                "Kolor:": "Czarny",
                "Poj.": "silnika: 999 cm³",
                "Stan": "techniczny: Uszkodzony",
                "Skrzynia": "biegów: Manualna",
                "Moc": "silnika: 100 KM"
            }
        },
        {
            "title": "Renault Megane Scenic LPG !!! Klimatyzacja !!!",
            "price": "4 900 złdo negocjacji",
            "link": "https://www.olx.pl/oferta/renault-megane-scenic-lpg-klimatyzacja-CID5-ID12zeIK.html",
            "description": "Witam, \n\nPosiadam na sprzedaż Renault Megane Scenic 1.6 benzyna z LPG ważnym do 21.03.2027\n\nRenault bardzo dobrze się prowadzi, nic nie stuka w zawieszeniu, prowadzi się pewnie. Wnętrze czyste i zadbane.\n\nZapraszam do kontaktu telefonicznego !!!",
            "details": {
                "Model:": "Scenic",
                "Rok": "produkcji: 2005",
                "Paliwo:": "LPG",
                "Typ": "nadwozia: Minivan",
                "Przebieg:": "350 000 km",
                "Kolor:": "Srebrny",
                "Poj.": "silnika: 1 600 cm³",
                "Stan": "techniczny: Nieuszkodzony",
                "Skrzynia": "biegów: Manualna",
                "Moc": "silnika: 112 KM",
                "Kierownica:": "po lewej"
            }
        },
        {
            "title": "Audi A-3 8P 2.0 TDI  // ekonomiczny // Klima // Zadbany // Zamiana //",
            "price": "4 990 złdo negocjacji",
            "link": "https://www.olx.pl/oferta/audi-a-3-8p-2-0-tdi-ekonomiczny-klima-zadbany-zamiana-CID5-ID14TKOA.html",
            "description": "Samochód zarejestrowany w kraju z ważnymi opłatami !!\n\nOferujemy usługę dostarczenia auta pod dom !!! \n\nDzień dobry dziś mamy dla państwa do zaprezentowania bardzo fajną i ekonomiczną Audi A-3 z silnikiem diesla o pojemności 2.0 i mocy 140 koni mechanicznych. Idealne autko dla początkującego kierowcy tanie w eksploatacji oraz oszczędne. Na chwilę obecną nie wymaga żadnych dodatkowych nakładów finansowych. Silnik odpala na dotyk pracuje równo i prawidłowo. Zawiesznie nie wybite prowadzi się pewnie i komfortowo. Wnętrze czyste i zadbane.\nW aucie ostatnio był wymieniony rozrząd około 8000km temu. Wizualnie bardzo ładnie się prezentuje. Cena oczywiście podlega negocjacji.\n\nNa wyposażeniu samochodu :\n\n- centralny zamek\n- wspomaganie kierownicy\n- regulowana kierownica \n- radio \n- tempomat\n- centralny zamek \n- ⁠ABS    \n- ESP\n\nSamochód posiada ważne ubezpieczenie OC !!!\n\nChętnie zamienimy !\n\nMamy dużo aut w podobnych cenach!\n\nZnajdujemy się przy ul Puławskiej 427 na parkingu centrum handlowego Ursynów obok stacji kontroli pojazdów. \n\nPrzed przyjazdem zadzwoń, zapytaj o dostępność wybranego autka ! \n\nKończy Ci sie ubezpieczenie lub przegląd? \nPrzyjmiemy Twoje auto w rozliczeniu!\n\nRezerwacja wybranego modelu mozliwa jedynie poprzez wplate zadatku !\n\nSKUPUJEMY WSZYSTKIE MARKI SAMOCHODÓW! \nWystawiamy Fakture VAT MARZA - Jesteście Państwo zwolnieni z oplaty skarbowej 2% :) !\n\nGodziny otwarcia\nPoniedzialek-Sobota 10:00-20:00\nNiedziela 11:00-16:00 \nZapraszamy do kontaktu przez olx i telefonicznego 73*******09",
            "details": {
                "Model:": "A3",
                "Rok": "produkcji: 2005",
                "Paliwo:": "Diesel",
                "Typ": "nadwozia: Hatchback",
                "Przebieg:": "290 000 km",
                "Kolor:": "Szary",
                "Poj.": "silnika: 2 000 cm³",
                "Stan": "techniczny: Nieuszkodzony",
                "Skrzynia": "biegów: Manualna",
                "Moc": "silnika: 140 KM",
                "Napęd:": "Na przednie koła",
                "Kierownica:": "po lewej"
            }
        },
        {
            "title": "Citroen c4 picasso",
            "price": "6 900 złdo negocjacji",
            "link": "https://www.olx.pl/oferta/citroen-c4-picasso-CID5-ID156Lwd.html",
            "description": "Witam oszczędne i sprawne autko rodzinne , przestronne wnętrze oraz silniczek 1.6 diesel sprawia ze auto naprawie przyjemnie się prowadzi wszytko robione na czas , auto posiada hak holowniczy oraz siedem miejsc , jedynym minusem jest to że fotel kierowcy jest trochę zniszczony zapraszam prv",
            "details": {
                "Model:": "C4 Picasso",
                "Rok": "produkcji: 2008",
                "Paliwo:": "Diesel",
                "Typ": "nadwozia: Minivan",
                "Przebieg:": "320 000 km",
                "Kolor:": "Czarny",
                "Poj.": "silnika: 1 600 cm³",
                "Stan": "techniczny: Nieuszkodzony",
                "Skrzynia": "biegów: Manualna"
            }
        },
        {
            "title": "Renault Espace III  2.2dCi Łódź",
            "price": "5 900 złdo negocjacji",
            "link": "https://www.olx.pl/oferta/renault-espace-iii-2-2dci-lodz-CID5-ID15edK9.html",
            "description": "Witam na sprzedaż posiadam Van Renault Espace III  z 18-07-2002 . Jestem pierwszym i jedynym  właścicielem w Polsce tego samochodu zarejestrowany 21-04-2005 . Auto używane było do celów prywatnych . Rok temu został wymieniony rozrząd z pompą wodną a pod koniec października wymieniono na nowy tylny prawy zacisk hamulca wymieniono na inna używaną maglownice . Jednym z wielu zalet tego samochodu jest możliwość szybkiego demontażu drugiego rzędu foteli i Van przeradza się w Bus ponieważ dużo zwiększa się kubatura a co za tym idzie powierzchnia ładowania (można zabrać na wakacje do środka rowery bez składania lub na materacach dmuchanych można się wygodnie wyspać  bez rozbijania namiotu ) . Auto jak na swoje lata jest w dobrym stanie jednak ma niepilne naprawy n.p. klimatyzacje  działała ale ponieważ nie była używana teraz nie chłodzi .  \n   Zapraszam do oglądania i kupna wystawionego samochodu . Odpowiadam telefonicznie na Państwa pytania .",
            "details": {
                "Numer": "VIN: VF8JE0K0526930343",
                "Model:": "Espace",
                "Rok": "produkcji: 2002",
                "Paliwo:": "Diesel",
                "Typ": "nadwozia: Minivan",
                "Przebieg:": "263 206 km",
                "Kolor:": "Szary",
                "Poj.": "silnika: 2 188 cm³",
                "Stan": "techniczny: Nieuszkodzony",
                "Skrzynia": "biegów: Manualna",
                "Kraj": "pochodzenia: Niemcy",
                "Moc": "silnika: 150 KM",
                "Napęd:": "Na przednie koła",
                "Kierownica:": "po prawej"
            }
        },
        {
            "title": "VW Passat 1.9 tdi. Możliwa zamiana",
            "price": "2 499 zł",
            "link": "https://www.olx.pl/oferta/vw-passat-1-9-tdi-mozliwa-zamiana-CID5-ID15eflx.html",
            "description": "Witam serdecznie. Sprzedam widocznego na zdjęciach Passata. Samochód oszczędny, żwawy, sprawny technicznie, dużo nowych części w zawieszeniu. Auto odpala na półobrotu kluczyka. Niestety strona wizualna nie jest tak bardzo powalająca, ale auto trzyma sie w calości. Dobre na budowę albo dojazdy do pracy. Sprawna klimatyzacja, 4elektryczne szyby, kontrola trakcji, posiada ważne ubezpieczenie, niestety przegląd się skończył. Cena jaka mnie interesuje za auto to 2,500tys zł. \nDo negocjacji lub ewenwtualna zamiana na auto w benzynie, ponieważ mam krótkie dystanse do pracy i disiel mi nie potrzebny. Samochód do obejrzenia na Żoliborzu. Pozdrawiam serdecznie, Mietek.",
            "details": {
                "Model:": "Passat",
                "Rok": "produkcji: 2000",
                "Paliwo:": "Diesel",
                "Typ": "nadwozia: Kombi",
                "Przebieg:": "269 000 km",
                "Kolor:": "Srebrny",
                "Poj.": "silnika: 1 cm³",
                "Stan": "techniczny: Nieuszkodzony",
                "Skrzynia": "biegów: Manualna",
                "Moc": "silnika: 110 KM",
                "Napęd:": "Na przednie koła",
                "Kierownica:": "po lewej"
            }
        },
        {
            "title": "Ładna Astra H 1.8 LPG bez korozji*zarejestrowana*ważne opłaty",
            "price": "7 900 złdo negocjacji",
            "link": "https://www.olx.pl/oferta/ladna-astra-h-1-8-lpg-bez-korozjizarejestrowanawazne-oplaty-CID5-ID15eeWu.html",
            "description": "Witam \nDo sprzedaży oferuje bardzo ladnego I zadbanego Opel Astra H z roku 2004 z sekwencyjna instalacja gazowa sekwencja wazna do 2030r i butla w kole\nAuto zarejestrowane na polskich tablicach \nOc do lipca \nPrzegląd do grudnia \nTapicerka welurowa czysta bez zniszczeń zadbana \nBez oznak korozji \nStan techniczny bez zastrzeżeń \nMożliwość przyjęcia auta w rozliczeniu \nKupujący zwolniony z opłaty skarbowej \nWiecej informacji telefonicznie",
            "details": {
                "Model:": "Astra",
                "Rok": "produkcji: 2004",
                "Paliwo:": "LPG",
                "Typ": "nadwozia: Hatchback",
                "Przebieg:": "312 000 km",
                "Kolor:": "Srebrny",
                "Poj.": "silnika: 1 800 cm³",
                "Stan": "techniczny: Nieuszkodzony",
                "Skrzynia": "biegów: Manualna",
                "Kraj": "pochodzenia: Polska",
                "Moc": "silnika: 125 KM",
                "Napęd:": "Na przednie koła",
                "Kierownica:": "po lewej"
            }
        },
        {
            "title": "Ładne ekonomiczne CLIO 3 1,5",
            "price": "4 300 złdo negocjacji",
            "link": "https://www.olx.pl/oferta/ladne-ekonomiczne-clio-3-1-5-CID5-ID141QRS.html",
            "description": "Na sprzedaż Clio 3 z 2008 roku, 1,5dci, bardzo ekonomiczny i oszczędny spalanie w mieście waha się między 5-5,5 litra ropy co uważam że jest bardzo dobrym wynikiem, auto wyposażone w elektryczne szyby, elektryczne lusterka, centralny zamek, wspomaganie kierownicy, klimatyzacja, ABS, radio oryginalne ze sterowaniem przy kierownicy, poduszki powietrzne, w aucie w ostatnim roku zrobione sporo napraw między innymi regeneracja pompy wtryskowej, regeneracja wtryskiwaczy, regeneracja turbosprężarki, nowy rozrusznik, nowy akumulator. Auto w tym momencie uważam że bez wkładu finansowego gotowe do jazdy, cena atrakcyjna przy kosztach zrobionych napraw, polecam 51*****64",
            "details": {
                "Model:": "Clio",
                "Rok": "produkcji: 2008",
                "Paliwo:": "Diesel",
                "Typ": "nadwozia: Hatchback",
                "Przebieg:": "360 000 km",
                "Kolor:": "Czerwony",
                "Poj.": "silnika: 1 500 cm³",
                "Stan": "techniczny: Nieuszkodzony",
                "Skrzynia": "biegów: Manualna",
                "Kraj": "pochodzenia: Niemcy",
                "Kierownica:": "po lewej"
            }
        },
        {
            "title": "Mercedes C 200 Kompresor z LPG Automat Avangarde Okazja Gotowy do Jazd",
            "price": "6 900 złdo negocjacji",
            "link": "https://www.olx.pl/oferta/mercedes-c-200-kompresor-z-lpg-automat-avangarde-okazja-gotowy-do-jazd-CID5-ID15ef7j.html",
            "description": "Witam, \n\nNa sprzedaż posiadam Mercedesa C200 kompresor z 2002r. \nAuto w bardzo dobrym stanie mechanicznym, po wymianie zawieszenia tył oraz wcześniej regeneracji skrzyni biegów. Auto wyposażone oczywiście w automatyczną skrzynię płynnie zmieniająca biegi.\nSilnik 2.0 o mocy 163 km daje radę a wyposażony w instalację gazową sprawia że jest ekonomiczny. \nOczywiście jak to Mercedes naloty rdzy posiada aczkolwiek są zabezpieczone i dziur nie ma. \nAuto ma oczywiście aktualne opłaty \nKlimatyzacja sprawa \nWnętrze mega zadbane czysxiutkie i pachnące \nGotowe do jazdy \n\nZapraszam konkretnych klientów którzy chcą poczuć ten komfort i prestiż jadąc z celownikiem",
            "details": {
                "Model:": "C Klasa",
                "Rok": "produkcji: 2002",
                "Paliwo:": "LPG",
                "Typ": "nadwozia: Kombi",
                "Przebieg:": "361 523 km",
                "Kolor:": "Inny kolor",
                "Poj.": "silnika: 2 000 cm³",
                "Stan": "techniczny: Nieuszkodzony",
                "Skrzynia": "biegów: Automatyczna",
                "Kraj": "pochodzenia: Polska",
                "Moc": "silnika: 163 KM",
                "Napęd:": "Na tylne koła",
                "Kierownica:": "po lewej"
            }
        }
    ]
}