{
    "updated": "2025-04-02 20:34:00.031400",
    "ads": [
        {
            "title": "Peugeot 307 SW 2.0 Benzyna+Gaz klima",
            "price": "3 500 zł",
            "link": "https://www.olx.pl/oferta/peugeot-307-sw-2-0-benzyna-gaz-klima-CID5-ID15f8dj.html",
            "location": "Wolbórz",
            "date": "02 April 2025 o 20:26",
            "description": "Na sprzedaż Peugeot 307 SW 2.0 136km rok produkcji 2003 przebieg 312400tys.  Z instrukcją gazową ważną do 2033 roku.  Ubezpieczenie OC do 27.12.2025.\nBadanie techniczne do 05.02.2026.\n6 miesięcy temu wymieniony wydech, tarcze+klocki tył , Ole i filtry , świece i cewki zapłonowe, 1 rok temu akumulator.  \nNa benzynie nie równa praca silnika po przełączeniu na gaz równa praca i nie ma żadnych problemów.\nWyposażenie:\nKlimatyzacja,\nABS,\nCentralny zamek,\nRadio fabryczne,\nPoduszki powietrzne,\nElektryczne szyby,\nElektryczne lusterka,\nHak , \nDodatkowy komplet kół zimowych.\nZapraszam do kontaktu 69*******85 .",
            "details": {
                "Model": "307 SW",
                "Rok produkcji": "2003",
                "Paliwo": "Benzyna",
                "Typ nadwozia": "Kombi",
                "Przebieg": "312 400 km",
                "Kolor": "Inny kolor",
                "Poj. silnika": "2 000 cm³",
                "Stan techniczny": "Nieuszkodzony",
                "Skrzynia biegów": "Manualna",
                "Moc silnika": "136 KM",
                "Napęd": "Na przednie koła"
            },
            "image_url": "https://ireland.apollo.olxcdn.com:443/v1/files/scshegyteh8n3-PL/image;s=1500x2000"
        },
        {
            "title": "BMW E60 520D 163PS 2007 po lift anglik Zarejestrowany",
            "price": "8 200 zł",
            "link": "https://www.olx.pl/oferta/bmw-e60-520d-163ps-2007-po-lift-anglik-zarejestrowany-CID5-ID15d0xB.html",
            "location": "Zgierz",
            "date": "02 April 2025 o 20:16",
            "description": "Witam sprzedam lub zamienię \n\nBMW E60 520D 163PS 2007 \nZ Manualną 6 Biegowa skrzynią po lift  jest to Anglik zarejestrowany \n\nStan techniczny autka oceniam na bardzo dobry samochód jest W 100% sprawny silnik skrzynia biegów zawieszenie sprzęgło w super stanie autko nie ściąga na lewo na prawo trzyma się pewnie drogi \n\nStan wizualny autka jak na zdjęciach autko jest czyste zadbane nie poniszczone w oryginalnym lakierze \n\nPo więcej informacji zapraszam priv pozdrawiam",
            "details": {
                "Model": "Seria 5",
                "Rok produkcji": "2007",
                "Paliwo": "Diesel",
                "Typ nadwozia": "Sedan",
                "Przebieg": "353 000 km",
                "Kolor": "Niebieski",
                "Poj. silnika": "1 995 cm³",
                "Stan techniczny": "Nieuszkodzony",
                "Skrzynia biegów": "Manualna",
                "Kraj pochodzenia": "Wielka Brytania",
                "Moc silnika": "163 KM",
                "Napęd": "Na tylne koła",
                "Kierownica": "po prawej"
            },
            "image_url": "https://ireland.apollo.olxcdn.com:443/v1/files/ci2waqag3uh7-PL/image;s=1000x750"
        },
        {
            "title": "Toyota Avensis sprzedam",
            "price": "4 200 zł",
            "link": "https://www.olx.pl/oferta/toyota-avensis-sprzedam-CID5-ID15f7ZT.html",
            "location": "Miłocin",
            "date": "02 April 2025 o 20:15",
            "description": "Sprzedam Toyote Avensis\nPodgrzewane siedzenia\nMultifunkcyjna kierownica\n6 biegowa skrzynia\nTempomat\nElektrycznie ustawiane lusterka\nOstatnio wymienione zostały tarcze przednie, filtry i olej\nDo wymiany wtryski\nUbezpieczenie do maja\nPrzegląd do listopada",
            "details": {
                "Model": "Avensis",
                "Rok produkcji": "2005",
                "Paliwo": "Diesel",
                "Typ nadwozia": "Kombi",
                "Przebieg": "388 888 km",
                "Kolor": "Srebrny",
                "Poj. silnika": "2 200 cm³",
                "Stan techniczny": "Uszkodzony",
                "Skrzynia biegów": "Manualna",
                "Moc silnika": "177 KM",
                "Kierownica": "po lewej"
            },
            "image_url": "https://ireland.apollo.olxcdn.com:443/v1/files/c72716dc6cl12-PL/image;s=576x1020"
        },
        {
            "title": "MINI ONE 1.6B 90KM zwinne miejskie fajne auto długie oc Od właściciela",
            "price": "7 500 zł",
            "link": "https://www.olx.pl/oferta/mini-one-1-6b-90km-zwinne-miejskie-fajne-auto-dlugie-oc-od-wlasciciela-CID5-ID154o2I.html",
            "location": "Chotomów",
            "date": "02 April 2025 o 20:09",
            "description": "Sprzedam Kultowe autko\nAuto zostało sprowadzone od rodziny z Niemiec w 2017 r \n2 właścicieli \nserwisowane \nPełna dokumentacja \nOc do 01.2026 \nPrzegląd techniczny do 03.2026 \nFajne zwinne miejskie auto do jazdy\nZapraszam oferta prywatna\nCena do rozsądnej negocjacji \nKontakt tylko telefoniczny",
            "details": {
                "Numer VIN": "wmwra31090ta03871",
                "Model": "One",
                "Rok produkcji": "2002",
                "Paliwo": "Benzyna",
                "Typ nadwozia": "Hatchback",
                "Przebieg": "250 000 km",
                "Kolor": "Czarny",
                "Poj. silnika": "1 598 cm³",
                "Stan techniczny": "Nieuszkodzony",
                "Skrzynia biegów": "Manualna",
                "Kraj pochodzenia": "Niemcy",
                "Moc silnika": "90 KM",
                "Napęd": "Na przednie koła",
                "Kierownica": "po lewej"
            },
            "image_url": "https://ireland.apollo.olxcdn.com:443/v1/files/erpq6ps4yvu52-PL/image;s=884x447"
        },
        {
            "title": "Dodge avenger 2.0lpg uszkodozny",
            "price": "2 700 zł",
            "link": "https://www.olx.pl/oferta/dodge-avenger-2-0lpg-uszkodozny-CID5-ID15f7GJ.html",
            "location": "Warszawa, Białołęka",
            "date": "02 April 2025 o 20:08",
            "description": "Sprzedam auto z uszkodzonym silnikiem , odpala ale stuka prawdopodobnie panewka zapraszam",
            "details": {
                "Model": "Avenger",
                "Rok produkcji": "2007",
                "Paliwo": "LPG",
                "Typ nadwozia": "Sedan",
                "Przebieg": "316 100 km",
                "Kolor": "Czarny",
                "Poj. silnika": "1 986 cm³",
                "Stan techniczny": "Uszkodzony",
                "Skrzynia biegów": "Manualna",
                "Kraj pochodzenia": "Szwajcaria",
                "Moc silnika": "156 KM",
                "Napęd": "Na przednie koła",
                "Kierownica": "po lewej"
            },
            "image_url": "https://ireland.apollo.olxcdn.com:443/v1/files/ayna824v7s7w1-PL/image;s=1000x750"
        },
        {
            "title": "Peugeot 206 SW! 1.4 HDI! Bez korozji! Klimatyzacja!",
            "price": "4 700 zł",
            "link": "https://www.olx.pl/oferta/peugeot-206-sw-1-4-hdi-bez-korozji-klimatyzacja-CID5-ID15f7Ft.html",
            "location": "Sochaczew",
            "date": "02 April 2025 o 20:07",
            "description": "Sprzedam Peugeot 206 z silnikiem 1.4 HDI. Auto ładne bez korozji. Silnik i zawieszenie w super stanie. Silnik po serwisie olejowym. Auto wyposażone w centralny zamek, wspomaganie kierownicy, klimatyzacje, ABS, poduszki powietrzne. Samochód posiada ważny przegląd i ubezpieczenie. Więcej informacji udzielę telefonicznie, proszę dzwonić.",
            "details": {
                "Model": "206",
                "Rok produkcji": "2004",
                "Paliwo": "Diesel",
                "Typ nadwozia": "Kombi",
                "Przebieg": "226 000 km",
                "Kolor": "Inny kolor",
                "Poj. silnika": "1 400 cm³",
                "Stan techniczny": "Nieuszkodzony",
                "Skrzynia biegów": "Manualna",
                "Kraj pochodzenia": "Francja",
                "Moc silnika": "68 KM",
                "Napęd": "Na przednie koła",
                "Kierownica": "po lewej"
            },
            "image_url": "https://ireland.apollo.olxcdn.com:443/v1/files/rqioddj33dvk1-PL/image;s=2048x1532"
        },
        {
            "title": "Niebieski Peugeot 207",
            "price": "7 000 zł",
            "link": "https://www.olx.pl/oferta/niebieski-peugeot-207-CID5-ID15f7mC.html",
            "location": "Podebłocie",
            "date": "02 April 2025 o 20:07",
            "description": "Witam na sprzedaż Peugeot 207 z benzynowym silnikiem 1,6. Samochód nie duży zwinny z ładnym wnętrzem \nWszystkie serwisy wykonywane na bieżąco . Samochód posiada czujniki parkowania tył, 4x elektryczne szyby oraz elektryczne lusterka. Letnie opony mogę dorzucić gratis. \nOC ważne do 22.07.2025r i przegląd ważny do 17.07.2025r \nZainteresowanych zapraszam na oględziny i jazdę próbną 50*****07",
            "details": {
                "Numer VIN": "VF3WC5FWC33874693",
                "Model": "207",
                "Rok produkcji": "2007",
                "Paliwo": "Benzyna",
                "Typ nadwozia": "Hatchback",
                "Przebieg": "249 673 km",
                "Kolor": "Niebieski",
                "Poj. silnika": "1 598 cm³",
                "Stan techniczny": "Nieuszkodzony",
                "Skrzynia biegów": "Manualna",
                "Kraj pochodzenia": "Francja",
                "Moc silnika": "88 KM",
                "Kierownica": "po lewej"
            },
            "image_url": "https://ireland.apollo.olxcdn.com:443/v1/files/ffh2nup4vx3q3-PL/image;s=1000x990"
        },
        {
            "title": "Citroen c5 2.2 automat",
            "price": "3 400 zł",
            "link": "https://www.olx.pl/oferta/citroen-c5-2-2-automat-CID5-ID157QJK.html",
            "location": "Węgrzynowo",
            "date": "02 April 2025 o 20:06",
            "description": "Sprzedam citroena c5 z 2004 roku \nSilnik 2.2 diesel \nSkrzynia biegów automatyczna \nStan ogólny blacharski i mechaniczny dobry \nOpłaty do maja\nNie działa prędkościomierz \n57*******67",
            "details": {
                "Model": "C5",
                "Rok produkcji": "2004",
                "Paliwo": "Diesel",
                "Typ nadwozia": "Kombi",
                "Przebieg": "313 km",
                "Kolor": "Czarny",
                "Poj. silnika": "2 200 cm³",
                "Stan techniczny": "Nieuszkodzony",
                "Skrzynia biegów": "Automatyczna",
                "Kraj pochodzenia": "Austria",
                "Moc silnika": "111 KM",
                "Napęd": "Na przednie koła",
                "Kierownica": "po lewej"
            },
            "image_url": "https://ireland.apollo.olxcdn.com:443/v1/files/ouq21iidiq5k1-PL/image;s=1000x750"
        },
        {
            "title": "Sprzedam chevrolet kalos",
            "price": "3 000 zł",
            "link": "https://www.olx.pl/oferta/sprzedam-chevrolet-kalos-CID5-ID15f7yp.html",
            "location": "Lubochnia",
            "date": "02 April 2025 o 20:05",
            "description": "Witam posiadam na sprzedaż chevroleta Kalosa z 2006 roku . Samochód w pełni sprawny technicznie\nNa lakierze pojedyncze obcierki , bez rdzy.",
            "details": {
                "Model": "Kalos",
                "Rok produkcji": "2006",
                "Paliwo": "Benzyna",
                "Typ nadwozia": "Hatchback",
                "Przebieg": "192 000 km",
                "Kolor": "Srebrny",
                "Poj. silnika": "1 200 cm³",
                "Stan techniczny": "Nieuszkodzony",
                "Skrzynia biegów": "Manualna"
            },
            "image_url": "https://ireland.apollo.olxcdn.com:443/v1/files/iq8vszhnr1r23-PL/image;s=1536x2048"
        },
        {
            "title": "Skoda Octavia 2.0 benzyna+LPG",
            "price": "4 500 zł",
            "link": "https://www.olx.pl/oferta/skoda-octavia-2-0-benzyna-lpg-CID5-ID15f7lL.html",
            "location": "Wąglany",
            "date": "02 April 2025 o 20:03",
            "description": "Sprzedam Skodę octavia 2.0 benzyna gaz, z 2000roku, autko po znajomym.\nSamochód sprawny,  pracuje równo na gazie jak i na benzynie ale jest do przejrzenia zawieszenie przód, coś czasem stuknie\nŚwieży przegląd \nKlimatyzacja, 4x el. szyby\nSamochód do obejrzenia na miejscu bądź w Piotrkowie Trybunalskim po wcześniejszym kontakcie telefonicznym.\nWięcej informacji pod numerem tel.",
            "details": {
                "Numer VIN": "TMBHE21U912431279",
                "Model": "Octavia",
                "Rok produkcji": "2000",
                "Paliwo": "LPG",
                "Typ nadwozia": "Kombi",
                "Przebieg": "290 565 km",
                "Kolor": "Srebrny",
                "Poj. silnika": "1 984 cm³",
                "Stan techniczny": "Nieuszkodzony",
                "Skrzynia biegów": "Manualna",
                "Kraj pochodzenia": "Polska"
            },
            "image_url": "https://ireland.apollo.olxcdn.com:443/v1/files/krq2d5fm02db3-PL/image;s=2000x1128"
        },
        {
            "title": "Volvo V50 2.0D",
            "price": "3 500 zł",
            "link": "https://www.olx.pl/oferta/volvo-v50-2-0d-CID5-ID151bt1.html",
            "location": "Lublin",
            "date": "02 April 2025 o 20:01",
            "description": "Witam, podmiotem sprzedaży jest samochód Volvo V50. Auto jest z 2005 roku, pochodzi z Włoch. Został sprowadzony w 2009/10 roku do Polski. Od sierpnia 2024 jestem właścicielem i od tego momentu zostało w aucie zrobione: \n- hamulce przód, tył \n- amortyzatory tył \n- olej, filtry \n- łączniki stabilizatora z przodu \n- wiązka czujnika turbosprężarki \nZ wyposażenia dodałem tempomat, komputer pokładowy oraz wgrałem tłumaczenie na język polski. Przez dwóch ostatnich właścicieli w samochodzie było regenerowane turbo, wymienione świece żarowe, wymieniony rozrząd, opony. Niestety wszystkiego dokładnie nie pamiętam, ale lista jest spora. Na większość rzeczy jest dokumentacja potwierdzająca naprawy. W ostatnim czasie auto uległo uszkodzeniu. Samochód raczej z przeznaczeniem na części, gdyż jego naprawa jest już nieopłacalna, aczkolwiek ktoś kto ma możliwości jest w stanie go naprawić. Cena tak jak w ogłoszeniu, do rozsądnych negocjacji a nie pt. „Daje 1200 i zabieram dzisiaj”.",
            "details": {
                "Numer VIN": "YV1MW753152093132",
                "Model": "V50",
                "Rok produkcji": "2005",
                "Paliwo": "Diesel",
                "Typ nadwozia": "Kombi",
                "Przebieg": "288 427 km",
                "Kolor": "Szary",
                "Poj. silnika": "1 997 cm³",
                "Stan techniczny": "Uszkodzony",
                "Skrzynia biegów": "Manualna",
                "Kraj pochodzenia": "Włochy",
                "Moc silnika": "136 KM",
                "Napęd": "Na przednie koła",
                "Kierownica": "po lewej"
            },
            "image_url": "https://ireland.apollo.olxcdn.com:443/v1/files/soudfadc7p361-PL/image;s=1000x750"
        },
        {
            "title": "Czarny Citroen C2",
            "price": "4 500 zł",
            "link": "https://www.olx.pl/oferta/czarny-citroen-c2-CID5-ID15f7mf.html",
            "location": "Kobyłka",
            "date": "02 April 2025 o 20:00",
            "description": "Sprzedam czarnego Citroena C2\nAuto do poprawek blacharsko lakierniczych, klimatyzacja, elektryczne szyby, wspomaganie, oc na pół roku\nMożliwa zamiana na inne auto \nWięcej informacji pod numerem telefonu 45*****24",
            "details": {
                "Model": "C2",
                "Rok produkcji": "2004",
                "Paliwo": "Benzyna",
                "Typ nadwozia": "Hatchback",
                "Przebieg": "239 783 km",
                "Kolor": "Czarny",
                "Poj. silnika": "1 124 cm³",
                "Stan techniczny": "Nieuszkodzony",
                "Skrzynia biegów": "Manualna",
                "Napęd": "Na przednie koła",
                "Kierownica": "po lewej"
            },
            "image_url": "https://ireland.apollo.olxcdn.com:443/v1/files/w1vrkkd5k4oh-PL/image;s=1024x768"
        },
        {
            "title": "Mercedes A klasa 1.9 benzyna + LPG Długie opłaty, dobry stan, Warto",
            "price": "2 990 zł",
            "link": "https://www.olx.pl/oferta/mercedes-a-klasa-1-9-benzyna-lpg-dlugie-oplaty-dobry-stan-warto-CID5-ID15cZp3.html",
            "location": "Łódź, Bałuty",
            "date": "02 April 2025 o 20:00",
            "description": "Witam posiadam na sprzedaż Mercedesa A klasę z silnikiem 1.9 benzyna + LPG 125km, Długie opłaty. Bardzo dynamiczny a zarazem ekonomiczny. Mercedes jak na swoje lata w bardzo dobrym stanie, nie wymaga wkładu finansowego. Jeździ na benzynie i gazie, zawieszenie nie posiada żadnych luzów. Opony wielosezonowe w dobrym stanie.\nUbezpieczenie oraz przegląd techniczny ważny aż do 10.09.2025r \nAuto idealnie nadaje się na dojazdy do pracy/szkoły czy do rozwożenia jedzenia. Blacharsko prezentuje się okej, Polecam. Więcej informacji udzielę telefonicznie",
            "details": {
                "Model": "A Klasa",
                "Rok produkcji": "1999",
                "Paliwo": "LPG",
                "Typ nadwozia": "Hatchback",
                "Przebieg": "290 000 km",
                "Kolor": "Szary",
                "Stan techniczny": "Nieuszkodzony",
                "Skrzynia biegów": "Manualna",
                "Napęd": "Na przednie koła"
            },
            "image_url": "https://ireland.apollo.olxcdn.com:443/v1/files/kzq83gppflbc-PL/image;s=1280x576"
        },
        {
            "title": "Żółte Renault Megane Coupe",
            "price": "2 000 zł",
            "link": "https://www.olx.pl/oferta/zolte-renault-megane-coupe-CID5-ID15f733.html",
            "location": "Kobyłka",
            "date": "02 April 2025 o 19:53",
            "description": "Sprzedam Renault Megane do poprawek blacharsko lakierniczych \nAuto jeździ, skręca, hamuje, nic nie puka, OC na pół roku \nMożliwa zamiana na inne auto \nWięcej informacji pod numerem telefonu 45*****24",
            "details": {
                "Model": "Megane",
                "Rok produkcji": "2000",
                "Paliwo": "Benzyna",
                "Typ nadwozia": "Coupe",
                "Przebieg": "240 000 km",
                "Kolor": "Żółty – Złoty",
                "Poj. silnika": "1 598 cm³",
                "Stan techniczny": "Nieuszkodzony",
                "Skrzynia biegów": "Manualna",
                "Napęd": "Na przednie koła",
                "Kierownica": "po lewej"
            },
            "image_url": "https://ireland.apollo.olxcdn.com:443/v1/files/ya7x7xj3x3c73-PL/image;s=1024x768"
        },
        {
            "title": "Niebieski Peugeot 307",
            "price": "5 000 zł",
            "link": "https://www.olx.pl/oferta/niebieski-peugeot-307-CID5-ID15f6Op.html",
            "location": "Kobyłka",
            "date": "02 April 2025 o 19:48",
            "description": "Sprzedam Peugeota 1.6 HDi\nAuto sprawne, OC na pół roku, przegląd aktualny\nKlimatyzacja, elektryczne szyby i lusterka\nWięcej informacji pod numerem telefonu 45*****24\nMożliwa zamiana na inne auto",
            "details": {
                "Model": "307",
                "Rok produkcji": "2005",
                "Paliwo": "Diesel",
                "Typ nadwozia": "Kombi",
                "Przebieg": "252 521 km",
                "Kolor": "Niebieski",
                "Poj. silnika": "1 560 cm³",
                "Stan techniczny": "Nieuszkodzony",
                "Skrzynia biegów": "Manualna",
                "Napęd": "Na przednie koła",
                "Kierownica": "po lewej"
            },
            "image_url": "https://ireland.apollo.olxcdn.com:443/v1/files/b323lqp5pjzb2-PL/image;s=1024x768"
        },
        {
            "title": "Opel Astra H 1.6",
            "price": "8 000 zł",
            "link": "https://www.olx.pl/oferta/opel-astra-h-1-6-CID5-ID15f6Am.html",
            "location": "Nowe Boryszewo",
            "date": "02 April 2025 o 19:48",
            "description": "Samochod do jazdy, bez żadnego wkładu. OC ważne do 12.03.2026r. Przegląd do 13.01.2026. Rozrząd i pompa wody wymienione przy przebiegu 198tys km. Wymiana amortyzatorów i naprawa podwozia przy przebiegu 213 tys km. Założone nowe opony wielosezonowe 10.2023r. Wymieniony akumulator 12.2024r.",
            "details": {
                "Numer VIN": "W0L0AHL4868092774",
                "Model": "Astra",
                "Rok produkcji": "2006",
                "Paliwo": "Benzyna",
                "Typ nadwozia": "Hatchback",
                "Przebieg": "229 400 km",
                "Kolor": "Czarny",
                "Poj. silnika": "1 598 cm³",
                "Stan techniczny": "Nieuszkodzony",
                "Skrzynia biegów": "Manualna",
                "Kraj pochodzenia": "Niemcy",
                "Moc silnika": "105 KM",
                "Napęd": "Na przednie koła",
                "Kierownica": "po lewej"
            },
            "image_url": "https://ireland.apollo.olxcdn.com:443/v1/files/p0132tiayqbr3-PL/image;s=1024x768"
        },
        {
            "title": "Mitshubishi Galant Kombi 2.0 LPG",
            "price": "9 900 zł",
            "link": "https://www.olx.pl/oferta/mitshubishi-galant-kombi-2-0-lpg-CID5-ID15f6sZ.html",
            "location": "Stoczek Łukowski",
            "date": "02 April 2025 o 19:41",
            "description": "Witam sprzedam Mitsubishi Galant auto sprowadzone ok 6 lat temu z przebiegiem 110 tysięcy km przy 115 założony gaz firmy KME sprawuje się bardzo dobrze auto serwisowane na bieżąco w bardzo dobrym stanie technicznym i blacharskim. Jestem właścicielem auto zarejstrowane na mnie po zakupie przy 184 tysiącach zrobiłem spory serwis:\nWymiana kompletna rozrządu z pompa wody i napinaczem\nUszczelka pokrywy zaworów \nŁożysko przód\nPrzednie zaciski regenerowane\nNowe tylne tarcze I okładziny ręcznego \nWstawiony katalizator\nŁącznik elastyczny i tłumnik końcowy nowy.\nAuto stoi na bardzo ładnych czterech oponach uniroyal rainsport 5 dorzucam komplet stalówek z zimówkami. \nDelikatnie do poprawy ranty tylnich nadkoli lakierniczo. Blacharsko podloga i progi kielichy przednie i tylnie bardzo dobre bez problemu podnosi sie za progi. Mozliwosc sprawdzenia auta na stacji diagnostycznej.Więcej informacji udzielę telefonicznie.",
            "details": {
                "Model": "Galant",
                "Rok produkcji": "2001",
                "Paliwo": "LPG",
                "Typ nadwozia": "Kombi",
                "Przebieg": "197 000 km",
                "Kolor": "Szary",
                "Poj. silnika": "2 000 cm³",
                "Stan techniczny": "Nieuszkodzony",
                "Skrzynia biegów": "Manualna",
                "Kraj pochodzenia": "Niemcy",
                "Moc silnika": "136 KM",
                "Napęd": "Na przednie koła",
                "Kierownica": "po lewej"
            },
            "image_url": "https://ireland.apollo.olxcdn.com:443/v1/files/kxqbtz8cc4h31-PL/image;s=1156x867"
        },
        {
            "title": "Volvo V50 1.6d 2007 Czarny",
            "price": "6 000 zł",
            "link": "https://www.olx.pl/oferta/volvo-v50-1-6d-2007-czarny-CID5-ID154Rmn.html",
            "location": "Sulejówek",
            "date": "02 April 2025 o 19:39",
            "description": "Witam, sprzedaję swojego zasłużonego Volvo V50 z 2007 roku. Samochód użytkowałem 2 lata i był doskonałym kompanem przez cały ten okres. Robiony miał przy mnie rozrząd, wymieniona była odma, odświeżona turbina, nowe opony. Regularnie serwisowany oczywiście.\n\nSpcyfikaja:\n\nRok 2007\nSilnik 1.6d\nSkrzynia biegów manualna 5 biegów\nPrzebieg 370K (rozrząd zrobiony przy 342K)\nSkórzana tapicerka\nTempomat\nElektryczne szyby\n2 strefowa klimatyzacja\nHak\n2x Isofixy z tyłu\nŚwieżo po wymianie oleju/filtrów\nNowe opony\nPrzegląd techniczny będzie na dniach\nUbezpieczenie do 11 kwietnia\n\nJak widać na zdjęciach trochę jest obdrapany tu i tam czego nie ukrywam. Mimo wszystko jest to samochód miły dla oka. Nie chciałem inwestować w blacharkę, ale jak ktoś się na tym zna to to będzie kilka szybkich poprawek.",
            "details": {
                "Numer VIN": "YV1MW765272318675",
                "Model": "V50",
                "Rok produkcji": "2007",
                "Paliwo": "Diesel",
                "Typ nadwozia": "Kombi",
                "Przebieg": "370 000 km",
                "Kolor": "Czarny",
                "Poj. silnika": "1 560 cm³",
                "Stan techniczny": "Nieuszkodzony",
                "Skrzynia biegów": "Manualna",
                "Kraj pochodzenia": "Holandia",
                "Moc silnika": "109 KM",
                "Napęd": "Na przednie koła",
                "Kierownica": "po lewej"
            },
            "image_url": "https://ireland.apollo.olxcdn.com:443/v1/files/b1nwrkp5uv2l1-PL/image;s=4032x3024"
        },
        {
            "title": "Seat Ibiza 3, 2004 rok, 1.4 benzyna",
            "price": "4 000 zł",
            "link": "https://www.olx.pl/oferta/seat-ibiza-3-2004-rok-1-4-benzyna-CID5-ID14nQvt.html",
            "location": "Grabów nad Pilicą",
            "date": "02 April 2025 o 19:38",
            "description": "Sprzedam Seata Ibizę z roku 2004 benzyna bez gazu\n\nAuto było w moich rękach 4 lata i służyło do dojazdu do szkoły i pracy. Przez ten czas w samochodzie zrobione były łożyska w kołach, cylinderki w hamulcach bębnowych, rezystor od klimatyzacji, łączniki stabilizatora, założone były nowe świece w tamtym roku oraz została założona sportowa końcówka wydechu. Silnik chodzi bez zarzutu nie pobiera oleju, klima chłodzi i grzeje. Z minusów zamki w drzwiach się zacinają oraz zawieszenie jest do poprawy. Do samochodu dorzucam drugi komplet kół na lato. Przegląd i ubezpieczenie ważne do czerwca.",
            "details": {
                "Numer VIN": "VSSZZZ6LZ5D010118",
                "Model": "Ibiza",
                "Rok produkcji": "2004",
                "Paliwo": "Benzyna",
                "Typ nadwozia": "Hatchback",
                "Przebieg": "207 600 km",
                "Kolor": "Srebrny",
                "Stan techniczny": "Nieuszkodzony",
                "Skrzynia biegów": "Manualna",
                "Napęd": "Na przednie koła"
            },
            "image_url": "https://ireland.apollo.olxcdn.com:443/v1/files/nuvv2thi99261-PL/image;s=3060x4080"
        },
        {
            "title": "Ford Fiesta 1.25 2013 Czarny Anglik",
            "price": "10 000 zł",
            "link": "https://www.olx.pl/oferta/ford-fiesta-1-25-2013-czarny-anglik-CID5-ID154Tkq.html",
            "location": "Sulejówek",
            "date": "02 April 2025 o 19:37",
            "description": "Witam, sprzedaję swojego starego kompana, którego przywiozlem z odległej Irlandii. Samochód kupiłem w 2017 i zjeździłem nim całą Irlandię i połowę Europy. Nadal bardzo przyjemnie się nim jeździ, ale będzie wymagał trochę wkładu.\n\nSamochód jest w trakcie rejestracji w Polsce, tylko w zależności czy będzie on sprzedany na zrobienie czy na części możemy rejestrację sfinalizować. Kierownica jest nadal po prawej stronie, ale światła i lusterka zostały wymienione na europejskie. \n\nSamochód ma kilka obdrapań, pojawiła się korozja na nadkolu i miałem lekką stłuczę frontem.\n\nJestem otwarty na negocjację.",
            "details": {
                "Numer VIN": "WF0DXXGAKDCS67419",
                "Model": "Fiesta",
                "Rok produkcji": "2013",
                "Paliwo": "Benzyna",
                "Typ nadwozia": "Hatchback",
                "Przebieg": "180 000 km",
                "Kolor": "Czarny",
                "Poj. silnika": "1 242 cm³",
                "Stan techniczny": "Uszkodzony",
                "Skrzynia biegów": "Manualna",
                "Kraj pochodzenia": "Wielka Brytania",
                "Moc silnika": "81 KM",
                "Napęd": "Na przednie koła",
                "Kierownica": "po prawej"
            },
            "image_url": "https://ireland.apollo.olxcdn.com:443/v1/files/4ian3h1yiskp-PL/image;s=3024x4032"
        },
        {
            "title": "Subaru Forester 2.0 Benzyna+Gaz/Salon Polska/Serwisowany/4x4/Reduktor",
            "price": "6 900 zł",
            "link": "https://www.olx.pl/oferta/subaru-forester-2-0-benzyna-gaz-salon-polska-serwisowany-4x4-reduktor-CID5-ID13iRhS.html",
            "location": "Warszawa, Mokotów",
            "date": "02 April 2025 o 19:37",
            "description": "Sprzedam Subaru Forester zakupiony w polskim salonie sprzedaży w 2002 roku, odkupiony od drugiego właściciela , wyposażony w instalacje gazową marki Stag czyniącą jazdę ekonomiczną, średnie spalanie 12 litrów gazu, z napędem 4x4 i dodatkowo reduktorem napędu do jazdy w terenie, auto również wyposażone w hak wbity w dowód, 1500 kg może ciągnąć, auto serwisowane na bieżąco od początku do końca przez ASO i renomowany warsztat, książki serwisowe , mechanicznie zero wkładu, jeździ jak należy, dla wymagających do poprawek, głownie nadkola, reszta w miarę , progi całe, podłoga cała, zabezpieczana byłą, środek też nie poniszczony, fotele do przeprania może, na wyposażeniu między innymi sprawna klimatyzacja, szyberdach, szyby elektryczne, lusterka elektryczne, centralny zamek z pilota, radio, spryski reflektorów, halogeny  komputer pokładowy, alarm i inne, opony specjalne przeznaczone do Suva, bieżnik dobry, homologacja gazu do 2030 roku, ubezpieczenie do listopada 2025r. , przegląd techniczny do czerwca 2025r., do samochodu dwa oryginalne kluczyki z pilotami i alarmem",
            "details": {
                "Numer VIN": "jf1sg5lk43g007379",
                "Model": "Forester",
                "Rok produkcji": "2002",
                "Paliwo": "LPG",
                "Typ nadwozia": "SUV",
                "Przebieg": "470 000 km",
                "Kolor": "Czerwony",
                "Poj. silnika": "2 000 cm³",
                "Stan techniczny": "Nieuszkodzony",
                "Skrzynia biegów": "Manualna",
                "Kraj pochodzenia": "Polska",
                "Moc silnika": "125 KM",
                "Napęd": "4x4 (dołączany ręcznie)"
            },
            "image_url": "https://ireland.apollo.olxcdn.com:443/v1/files/3u6jywhkrvab2-PL/image;s=1024x768"
        },
        {
            "title": "Seat Toledo 1.6 2001r",
            "price": "3 500 zł",
            "link": "https://www.olx.pl/oferta/seat-toledo-1-6-2001r-CID5-ID15f673.html",
            "location": "Brzeziny",
            "date": "02 April 2025 o 19:34",
            "description": "Witam \nSorzedam seata telefonu z 2001r w dobrym stanie technicznym!\nSilninczek pracuje bardzo dobrze nie bierze oleju zawiewszenie okey progi podloga okey \nNowy rozrzad 15 tys km temu i sprzeglo nowe założone 3 miesiace temu \nOgolnie wsiadac I jezdzic",
            "details": {
                "Model": "Toledo",
                "Rok produkcji": "2001",
                "Paliwo": "Benzyna",
                "Typ nadwozia": "Sedan",
                "Przebieg": "300 000 km",
                "Kolor": "Niebieski",
                "Poj. silnika": "1 600 cm³",
                "Stan techniczny": "Nieuszkodzony",
                "Skrzynia biegów": "Manualna",
                "Moc silnika": "100 KM",
                "Napęd": "Na przednie koła",
                "Kierownica": "po lewej"
            },
            "image_url": "https://ireland.apollo.olxcdn.com:443/v1/files/fx2q3g7k0kvp-PL/image;s=1024x771"
        },
        {
            "title": "Audi A3 2003r 1,9 TDI 6 biegów",
            "price": "3 800 zł",
            "link": "https://www.olx.pl/oferta/audi-a3-2003r-1-9-tdi-6-biegow-CID5-ID15f61Y.html",
            "location": "Nowy Dwór Mazowiecki",
            "date": "02 April 2025 o 19:33",
            "description": "Sprzedam Audi A3 w  dobrym stanie mechanicznym, jeden właściciel 3 lata, Silnik ma moc , auto szybko się zbiera. 6-biegowa skrzynia biegów.  Wielokrotnie pokonywało trasę Polska-Holandia.\n Jedyny mankament to fotel do wymiany.\nLampy bi-ksenon, alufelgi do wyczyszczenia. \nBardzo długie opłaty. \nBez korozji, blacharka w bardzo dobrym stanie.\nZapraszam do oglądania",
            "details": {
                "Model": "A3",
                "Rok produkcji": "2003",
                "Paliwo": "Diesel",
                "Typ nadwozia": "Hatchback",
                "Przebieg": "400 000 km",
                "Kolor": "Czarny",
                "Poj. silnika": "1 900 cm³",
                "Stan techniczny": "Nieuszkodzony",
                "Skrzynia biegów": "Manualna",
                "Moc silnika": "150 KM",
                "Kierownica": "po lewej"
            },
            "image_url": "https://ireland.apollo.olxcdn.com:443/v1/files/u07ecr7adj5v3-PL/image;s=1500x1542"
        },
        {
            "title": "Volkswagen Polo 1.4 16V",
            "price": "6 300 zł",
            "link": "https://www.olx.pl/oferta/volkswagen-polo-1-4-16v-CID5-ID15f5AU.html",
            "location": "Warszawa, Targówek",
            "date": "02 April 2025 o 19:30",
            "description": "witam, mam na sprzedaż samochód Volkswagen Polo 1.4 16V w benzynie,\nstan bardzo dobry jak widać na zdjęciach,\nrok 2003,\nprzegląd ważny do listopada 2025\nOC do marca 2026\nauto posiada całkiem bogate wyposażenie jak na tamte czasy, elektryczne szyby, szyberdach\nposiadam komplet 4 opon letnich na zmianę\nauto jest sprowadzane z Niemiec (tam był 1 właściciel), kupiony w Polsce od 2 właściciela, a ja jestem 3,\nw aucie nie było palone \nfiltry i oleje wymieniane co roku po około 10 000 km,\nna przestrzeni lat odkąd posiadam samochód czyli 2020 roku w aucie zostały wymienione: \nsprzęgło 2021, alternator, akumulator 2023, zostały zrobione progi 2021, tarcze oraz klocki 2022, wymiana szyby z przodu 2023, wymiana skrzyni biegów 2022,\nw aucie też został dodany stożek, jak widać na zdjęciach pod maską,\n2 tygodnie temu zrobiłem serwis filtrów i olejów\nauto w stanie bardzo dobrym, zadbane, po więcej informacji zapraszam do kontaktu w wiadomości prywatnej albo proszę dzwonić/pisać SMS pod numer 51*****31",
            "details": {
                "Numer VIN": "WVWZZZ9NZ4Y020946",
                "Model": "Polo",
                "Rok produkcji": "2003",
                "Paliwo": "Benzyna",
                "Typ nadwozia": "Hatchback",
                "Przebieg": "180 000 km",
                "Kolor": "Zielony",
                "Poj. silnika": "1 390 cm³",
                "Stan techniczny": "Nieuszkodzony",
                "Skrzynia biegów": "Manualna",
                "Kraj pochodzenia": "Niemcy",
                "Moc silnika": "75 KM",
                "Napęd": "Na przednie koła",
                "Kierownica": "po lewej"
            },
            "image_url": "https://ireland.apollo.olxcdn.com:443/v1/files/rfhuw46em1ze-PL/image;s=750x1000"
        },
        {
            "title": "Opel Astra k 1.6 CDTI anglik",
            "price": "8 999 zł",
            "link": "https://www.olx.pl/oferta/opel-astra-k-1-6-cdti-anglik-CID5-ID15f5QV.html",
            "location": "Lućmierz",
            "date": "02 April 2025 o 19:29",
            "description": "Opel Astra k \n1.6 CDTI anglik \nCiężko pali nierówno chodzi \nWięcej informacji pod numerem telefonu \n\nNie odpowiadam na wiadomości",
            "details": {
                "Model": "Astra",
                "Rok produkcji": "2017",
                "Paliwo": "Diesel",
                "Typ nadwozia": "Kombi",
                "Przebieg": "120 000 km",
                "Kolor": "Inny kolor",
                "Stan techniczny": "Uszkodzony",
                "Skrzynia biegów": "Manualna"
            },
            "image_url": "https://ireland.apollo.olxcdn.com:443/v1/files/co44b9l7kfnm-PL/image;s=2000x1500"
        },
        {
            "title": "Sprzedam Citroen C5",
            "price": "3 500 zł",
            "link": "https://www.olx.pl/oferta/sprzedam-citroen-c5-CID5-ID1404xx.html",
            "location": "Elizówka",
            "date": "02 April 2025 o 19:29",
            "description": "Auto pochodzenia krajowego.   Jak widać na nim pełno przygód parkingowych, mi osobiście nic sie nie przytrafilo. Najwazniejsze dla mnie bylo zeby jezdzil i nie zawiodl mnie do tej pory. Butla wazna do 2031r.  Pneumatyka trzyma. Do poprawy podnośniki szyb elektrycznych.",
            "details": {
                "Model": "C5",
                "Rok produkcji": "2004",
                "Paliwo": "LPG",
                "Typ nadwozia": "Sedan",
                "Przebieg": "295 000 km",
                "Kolor": "Szary",
                "Poj. silnika": "1 795 cm³",
                "Stan techniczny": "Nieuszkodzony",
                "Skrzynia biegów": "Manualna",
                "Kraj pochodzenia": "Polska",
                "Napęd": "Na przednie koła",
                "Kierownica": "po lewej"
            },
            "image_url": "https://ireland.apollo.olxcdn.com:443/v1/files/b4nvew53rohz1-PL/image;s=2000x1126"
        },
        {
            "title": "Volkswagen Golf V 1.9  90KM",
            "price": "9 000 zł",
            "link": "https://www.olx.pl/oferta/volkswagen-golf-v-1-9-90km-CID5-ID14KF15.html",
            "location": "Niemce",
            "date": "02 April 2025 o 19:20",
            "description": "Witam. Na sprzedaż golf 5 rok produkcji 2007,  przebieg 313tys,moc 90km.  W moim posiadaniu od 4lat. W aucie wszystko robione na bieżąco na co mam rachunki i faktury. Przegląd ważny do lutego 2026r, ubezpieczenie do lipca 2025r. Dodaje opony letnie.\nCena do negocjacji.",
            "details": {
                "Model": "Golf",
                "Rok produkcji": "2007",
                "Paliwo": "Diesel",
                "Typ nadwozia": "Hatchback",
                "Przebieg": "313 518 km",
                "Kolor": "Srebrny",
                "Poj. silnika": "1 900 cm³",
                "Stan techniczny": "Nieuszkodzony",
                "Skrzynia biegów": "Manualna",
                "Moc silnika": "90 KM",
                "Napęd": "Na przednie koła"
            },
            "image_url": "https://ireland.apollo.olxcdn.com:443/v1/files/1hp3aft8gizx1-PL/image;s=1156x521"
        },
        {
            "title": "SAXO*1.1 Benzyna*2001r.*El. Szyby*Opłaty do Lipca*Sprawny Jeżdżący*",
            "price": "2 950 zł",
            "link": "https://www.olx.pl/oferta/saxo1-1-benzyna2001r-el-szybyoplaty-do-lipcasprawny-jezdzacy-CID5-ID15eCHG.html",
            "location": "Zgierz",
            "date": "02 April 2025 o 12:57",
            "description": "*** Pojazd do obejrzenia a terenie AUTO KOMISU W ZGIERZU PRZY UL. PIĄTKOWSKIEJ 85 ***\n\nMarka: Citroen Saxo\nSilnik : 1.1 stara, prosta benzyna\nSkrzynia biegów: 5 biegowa manualna\nMoc : 60 koni mechanicznych\nPrzebieg: 94700 km\nData produkcji: 2001 r.\nData 1 rej : 14.11.2001 r.\n\nPrzegląd ważny do: 07.2025\nUbezpieczenie OC ważne do: 07.2025\nBlacha ocynk - bez większych oznak korozji.\n\nWYPOSAŻENIE:\n- centralny zamek sterowany z kluczyka\n- AIR BAG kierowcy\n- radio CD\n- el. sterowane szyby przednie\n- brak wspomagania ale kierownicą kręci się dość lekko \n\nAuto sprawne i jeżdżące,  silnik pracuje równo, cicho i nie kopci, zawieszenie w miarę ok - choć jakieś delikatne stuki słychać ( poduszka amortyzatora) \n\nWady: z maski i dachu schodzi lakier bezbarwny.\nRewelacyjne spalanie ok 5-6 litrów na 100 km.\n\nWięcej informacji udzielę telefonicznie : 5 0 9 - 5 0 9 - 7 4 0\n\nNiniejsze ogłoszenie jest wyłącznie informacją handlową i nie stanowi oferty w myśl art. 66, paragraf 1. Kodeksu Cywilnego. Sprzedający nie odpowiada za ewentualne błędy lub nieaktualność ogłoszenia.\n\n***Przed przyjazdem obowiązkowo sprawdź aktualność oferty kontaktując się z przedstawicielem handlowym komisu pod nr tel : 5 0 9 - 5 0 9 - 7 4 0***",
            "details": {
                "Numer VIN": "VF7S1HFXB57466062",
                "Model": "Saxo",
                "Rok produkcji": "2001",
                "Paliwo": "Benzyna",
                "Typ nadwozia": "Hatchback",
                "Przebieg": "94 700 km",
                "Kolor": "Czerwony",
                "Poj. silnika": "1 124 cm³",
                "Stan techniczny": "Nieuszkodzony",
                "Skrzynia biegów": "Manualna",
                "Kraj pochodzenia": "Polska",
                "Moc silnika": "60 KM",
                "Napęd": "Na przednie koła",
                "Kierownica": "po lewej"
            },
            "image_url": "https://ireland.apollo.olxcdn.com:443/v1/files/czfhfazpankn2-PL/image;s=864x568"
        },
        {
            "title": "Volkswagen VW Touran 2.0 TDI 140KM DSG Automat",
            "price": "6 999 zł",
            "link": "https://www.olx.pl/oferta/volkswagen-vw-touran-2-0-tdi-140km-dsg-automat-CID5-ID15ejHR.html",
            "location": "Piaseczno",
            "date": "01 April 2025",
            "description": "Witam na sprzedaż ogłaszam VW Touran 2005r z najlepszym silnikiem 2.0 TDI 140KM. Automatyczna skrzynia DSG. \nSamochód w świetnym stanie technicznym nie potrzebuje żadnego nakładu finansowego poprostu siadać i jechać , autko serwisowane na bieżąco. Klimatyzacja sprawna. Bogate wyposażenie czujniki parkowania automat dsg nawigacja tempomat komputer pokładowy climatronic podgrzewane siedzenia aluminiowe felgi. Rok temu wymieniony kompletny rozrząd. Obecnie auto bez wkładu. \n\nData ważności polisy\n29.04.2025\n\nKupujący zwolniony z podatku pcc3",
            "details": {
                "Numer VIN": "WVGZZZ1TZ5W121660",
                "Model": "Touran",
                "Rok produkcji": "2005",
                "Paliwo": "Diesel",
                "Typ nadwozia": "Minivan",
                "Przebieg": "304 000 km",
                "Kolor": "Czarny",
                "Poj. silnika": "2 000 cm³",
                "Stan techniczny": "Nieuszkodzony",
                "Skrzynia biegów": "Manualna",
                "Moc silnika": "140 KM"
            },
            "image_url": "https://ireland.apollo.olxcdn.com:443/v1/files/a1uqqxxg3jy3-PL/image;s=1000x750"
        },
        {
            "title": "Opel Astra, 2005 rok 1.7 Isuzu– Otokomis! Gwarancji!",
            "price": "2 990 zł",
            "link": "https://www.olx.pl/oferta/opel-astra-2005-rok-1-7-isuzu-otokomis-gwarancji-CID5-ID15dyia.html",
            "location": "Warszawa, Włochy",
            "date": "01 April 2025",
            "description": "Zapraszamy do OTOKOMIS-Oferujemy szeroki wybór starannie wyselekcjonowanych samochodów.\n\nSpecyfikacja pojazdu:\nMarka: Opel\nModel: Astra\nRok produkcji: 2005\nSilnik: 1.7 diesel\nMoc: 110\nUbezpieczenie OC: jest ważne \nPrzegląd techniczny: jest ważne \n\nDlaczego warto wybrać ten samochód?\n\nAuto w dobrym stanie technicznym. Silnik chodzi ładnie nie dymi. Zawieszenie nie wybite. Jeździ skręca hamuje. Komuś jeszcze napewno posłuży.\n\nPolecam!!\n\nWyposażenie: alufelgi, klimatyzacja, ABS, radio CD, komputer pokładowy, wspomaganie kierownicy, wielofunkcyjna kierownica, elektryczne szyby i lusterka, centralny zamek\n\nGodziny otwarcia:\nPoniedziałek – Sobota: 10:00 – 20:00\nNiedziela: 11:00 – 16:00\nLokalizacja: Nasz plac znajduje się na parkingu centrum handlowego Lopuszańska 22.\n\nKontakt: Zadzwoń pod numer 518xx168xx153 i umów się na jazdę próbną!\n\nZapraszamy!",
            "details": {
                "Model": "Astra",
                "Rok produkcji": "2005",
                "Paliwo": "Diesel",
                "Typ nadwozia": "Hatchback",
                "Przebieg": "291 000 km",
                "Kolor": "Srebrny",
                "Poj. silnika": "1 700 cm³",
                "Stan techniczny": "Nieuszkodzony",
                "Skrzynia biegów": "Manualna",
                "Kraj pochodzenia": "Polska",
                "Moc silnika": "110 KM",
                "Napęd": "Na przednie koła",
                "Kierownica": "po lewej"
            },
            "image_url": "https://ireland.apollo.olxcdn.com:443/v1/files/iagoi3kmcq5w1-PL/image;s=1000x732"
        },
        {
            "title": "Na Sprzedaż/Opel Corsa/1.2/2003Rok/Zamiana/Nowe Klocki/Ekonomiczna",
            "price": "2 990 zł",
            "link": "https://www.olx.pl/oferta/na-sprzedaz-opel-corsa-1-2-2003rok-zamiana-nowe-klocki-ekonomiczna-CID5-ID15dvOJ.html",
            "location": "Warszawa, Włochy",
            "date": "01 April 2025",
            "description": "Samochód zarejestrowany w kraju\n\nOferujemy usluge dostarczenie auta pod dom.\n\nPrzyjmujemy auto w rozliczeniu !!!\n\nMożliwość kupienia samochodu w systemie ratalnym.\n\nWitam, posiadamy na sprzedaż piękny i niezawodny Opel Corsa z najlepszym niezawodnym silnikiem 1.2 Benzyna . Stan auta oceniam na bardzo dobry, ostatnio wymienione oleje oraz filtry, klocki. zawieszenie w bardzo dobrym stanie.\n\nNa wyposażeniu auta:\n- wspomaganie kierownicy\n- elektryczne szyby\n- klimatyzacja\n- centralny zamek z pilota\n- radio\n\nBlacharsko jak widać na zdjęciach w dość dobrym stanie.\nOpłaty ważne\nOC Ważne \nPT Ważne \n\nZapraszamy do oględzin oraz jazdę próbną.\n\nChętnie zamienimy!\n\nZapraszamy na Ryżowa 4, Warszawa.\n\nPrzed przyjazdem zadzwon, zapytaj o dostepnosc wybranego auta !\n\nPrzyjmiemy Twoje auto w rozliczeniu!\n\nWystawiamy Fakture VAT MARZA - Jestescie Panstwo zwolnieni z oplaty skarbowej 2% :) !\n\nGodziny otwarcia\n\nCodziennie od 10 do 20\n\nNiniejsze ogłoszenie nie stanowi oferty ani zapewnienia, w szczególności rozumieniu art. 66 § 1 i art. 556 indeks 1 Kodeksu cywilnego. Zastrzegamy sobie prawo do doprecyzowania oraz korekt omyłek.",
            "details": {
                "Model": "Corsa",
                "Rok produkcji": "2003",
                "Paliwo": "Benzyna",
                "Typ nadwozia": "Hatchback",
                "Przebieg": "170 000 km",
                "Kolor": "Czarny",
                "Poj. silnika": "1 200 cm³",
                "Stan techniczny": "Nieuszkodzony",
                "Skrzynia biegów": "Manualna",
                "Moc silnika": "70 KM",
                "Napęd": "Na przednie koła",
                "Kierownica": "po lewej"
            },
            "image_url": "https://ireland.apollo.olxcdn.com:443/v1/files/v7865o1e67192-PL/image;s=960x1280"
        },
        {
            "title": "Dodge Avenger 2.0 Diesel/2010 Rok/Dostawa pod dom/Gwarancja/Zamiana/",
            "price": "5 990 zł",
            "link": "https://www.olx.pl/oferta/dodge-avenger-2-0-diesel-2010-rok-dostawa-pod-dom-gwarancja-zamiana-CID5-ID14u52K.html",
            "location": "Ożarów Mazowiecki",
            "date": "01 April 2025",
            "description": "Autokomis TopCar Ul. Poznańska 308 Ożarów Mazowiecki \n\nMOŻLIWOŚĆ ZOSTAWIENIA \nAUTA W ROZLICZENIU !\n\nTAK ŻE OFERUJEMY USŁUGĘ DOSTARCZENIA AUTA POD DOM \n\nWitam wszystkich, na sprzedaż leci piękny i niezawodny Dodge Avenger wyprodukowany w 2010 Roku z najlepszym niezawodnym silnikiem 2.0 Diesel, autko jest zadbane i serwisowane zawsze na czas w tej chwili jest w 100% sprawne i nie potrzebuje wkładu finansowego, OC i PT jest aktualne tak że śmiało można wracać na kołach \n\nZ wyposażenia to:\n\n- Elektryczne 4 szyby \n- centralny zamek\n- podgrzewana tylna szyba\n- System ABS + EBD + EBA (z dynamiczna kontrola stabilnosci i kontroli jazdy)\n- wspomaganie kierownicy\n- Elektroniczny zegar\n- Elektroniczny termometr temp zewnetrznej\n- Kierownica regulowana w dwoch plazczyznach\n- Reczna regulacja wysokosci reflektorow\n- Aktywne zaglowki przednie\n-Tempomat\n- Komputer pokladowy obliczajacy srednie/chwilowe spalanie, zasieg auta itd\n- Mozliwosc ustawienia max predkosci w komputerze, ktorej samochod nie pozwoli nam przekroczyc\n- podgrzewane lusterka\n- sterowanie radiem z kierownicy\n- elektrycznie sterowane szyby (przod+tyl)\n- dwustrefowy klimatronik\n\nAutko jest w dobrym stanie zadbane i bardzo przyjemne w użytkowaniu \n\nCHĘTNIE ZAMIENIMY! \n\nRÓWNIEŻ SKUPUJEMY AUTA ZA GOTÓWKĘ ! \n\nZapraszamy na oglądanie i jazdę próbną \n\nAdres ul. Poznańska 308, Ożarów Mazowiecki \n\nOtwarte jest 7 Dni w tygodni\n\nW dni świąteczne również pracujemy \n\nOd 10:00 do 20:00\n\nWystawiam fakturę VAT-MARŻA, kupujący jest zwolniony z opłaty skarbowej!\n\nNiniejsze ogłoszenie jest wyłącznie informacją handlową i nie stanowi oferty w myśl art. 66, §1.Kodeksu Cywilnego. Sprzedający nie odpowiada za ewentualne błędy lub nieaktualność ogłoszenia.",
            "details": {
                "Model": "Avenger",
                "Rok produkcji": "2010",
                "Paliwo": "Diesel",
                "Typ nadwozia": "Sedan",
                "Przebieg": "328 000 km",
                "Kolor": "Czerwony",
                "Poj. silnika": "2 000 cm³",
                "Stan techniczny": "Nieuszkodzony",
                "Skrzynia biegów": "Manualna",
                "Napęd": "Na przednie koła",
                "Kierownica": "po lewej"
            },
            "image_url": "https://ireland.apollo.olxcdn.com:443/v1/files/r4r8vyr5sl4s1-PL/image;s=750x1000"
        },
        {
            "title": "SAAB 9-3 2.0 Turbo 2001 TRZYDRZWIOWY!",
            "price": "5 400 zł",
            "link": "https://www.olx.pl/oferta/saab-9-3-2-0-turbo-2001-trzydrzwiowy-CID5-ID13VndJ.html",
            "location": "Warszawa, Bielany",
            "date": "31 March 2025",
            "description": "SAAB 9-3 z 2001 roku na sprzedaż. Wersja z dwulitrowym silnikiem benzynowym turbo. Właścicielem jestem od kilku lat.\nLokalizacja: Warszawa \n\n+Przegląd do 18.02.26\n+OC do 08.09.25\n+ klimatyzacja\n+ wersja trzydrzwiowa\n+ ~230,000 km przebiegu\n+ sprowadzony kilka lat temu z Holandii na użytek własny\n+ ciemnogranatowy\n+ beżowa tapicerka\n+ pojemny bagażnik\n+ Nie działa: 1. radio - chociaż ma humorki i załącza się czasem po np. wjechaniu na 'policjanta' 2. pilot w kluczyku. Wszystko inne śmiga :-)\n+ Prawie nowe opony wielosezonowe\n+ w niektórych miejscach rdza - nadkola wymagają naprawy. Są zabezpieczone ale dziurki są :-)\n+ ręczna skrzynia biegów\n+ okna opuszczane elektrycznie\n\nGeneralnie fajne autko, ma moc i styl, SAABowy klasyk po prostu.",
            "details": {
                "Numer VIN": "ys3dd35cx12037128",
                "Model": "9-3",
                "Rok produkcji": "2001",
                "Paliwo": "Benzyna",
                "Typ nadwozia": "Coupe",
                "Przebieg": "230 000 km",
                "Kolor": "Inny kolor",
                "Poj. silnika": "1 985 cm³",
                "Stan techniczny": "Nieuszkodzony",
                "Skrzynia biegów": "Manualna",
                "Kraj pochodzenia": "Polska",
                "Moc silnika": "154 KM",
                "Napęd": "Na przednie koła",
                "Kierownica": "po lewej"
            },
            "image_url": "https://ireland.apollo.olxcdn.com:443/v1/files/lnbo8si79uy21-PL/image;s=4032x3024"
        }
    ]
}